[{"style":"cl","text":"Psalm 32"},{"style":"s1","text":"Thanksgiving for Forgiveness of Sins"},{"style":"d","text":"Of David. A maskil.\\f + \\fr Ps 32 \\ft The Hebrew Bible counts the superscription as the first verse of the psalm \\f*"},{"style":"q1","text":""},{"style":"v","text":"Happy \\add is\\add* he whose transgression is taken away,"},{"style":"q1","text":"whose sin is covered."},{"style":"q1","text":""},{"style":"v","text":"Happy \\add is\\add* a person to whom Yahweh does not impute iniquity"},{"style":"q1","text":"and in whose spirit there is not deceit."},{"style":"q1","text":""},{"style":"v","text":"When I kept silent, my bones were worn out"},{"style":"q1","text":"due to my groaning all the day."},{"style":"q1","text":""},{"style":"v","text":"For day and night your hand was heavy upon me."},{"style":"q1","text":"My vigor was changed into \\add the\\add* dry heat of summer. \\qs Selah\\qs*"},{"style":"q1","text":""},{"style":"v","text":"I made known my sin to you, and my iniquity I did not cover."},{"style":"q1","text":"I said, “I will confess concerning my transgressions to Yahweh,”"},{"style":"q1","text":"and you took away the guilt of my sin. \\qs Selah\\qs*"},{"style":"q1","text":""},{"style":"v","text":"Therefore let all \\add the\\add* faithful pray to you"},{"style":"q1","text":"at \\add the\\add* time \\add for\\add* finding \\add you\\add*."},{"style":"q1","text":"Surely at \\add the\\add* flood of many waters they will not reach him."},{"style":"q1","text":""},{"style":"v","text":"You \\add are\\add* my hiding place;"},{"style":"q1","text":"from trouble you preserve me."},{"style":"q1","text":"\\add With\\add* cries of deliverance you surround me. \\qs Selah\\qs*"},{"style":"q1","text":""},{"style":"v","text":"I\\f + \\fr 32:8 \\ft Yahweh is speaking in vv. \\xt 8–9 \\ft \\f* will instruct you and teach you"},{"style":"q1","text":"in \\add the\\add* way that you should go."},{"style":"q1","text":"I will advise \\add you\\add* \\add with\\add* my eye upon you."},{"style":"q1","text":""},{"style":"v","text":"Do not be like a horse \\add or\\add* like a mule, without understanding;"},{"style":"q1","text":"\\add that needs\\add* his tackle—bridle and rein—for restraint"},{"style":"q1","text":"\\add or he would not\\add* come near you."},{"style":"q1","text":""},{"style":"v","text":"Many are \\add the\\add* pains of the wicked,"},{"style":"q1","text":"but \\add for\\add* the one who trusts Yahweh"},{"style":"q1","text":"loyal love surrounds him."},{"style":"q1","text":""},{"style":"v","text":"Be glad in Yahweh and rejoice, \\add you\\add* righteous,"},{"style":"q1","text":"and shout for joy, all \\add you\\add* upright of heart."}]