[{"style":"s1","verse":"","text":"The Unfaithful Wife"},{"style":"sd0","verse":"","text":""},{"style":"q1","verse":"","text":""},{"style":"v","verse":"1","text":"Say to your brother,\\f + \\fr 2:1 \\ft Hebrew “brothers” \\f* “Ammi,”\\f + \\fr 2:1 \\ft Ammi means “My people” \\f*"},{"style":"q1","verse":"","text":"and to your sister,\\f + \\fr 2:1 \\ft Hebrew “sisters” \\f* “Ruhamah.”\\f + \\fr 2:1 \\ft Ruhamah means “Pitied” \\f*"},{"style":"q1","verse":"","text":""},{"style":"v","verse":"2","text":"Plead with your mother, plead—"},{"style":"q2","verse":"","text":"because she \\add is\\add* not my wife,"},{"style":"q3","verse":"","text":"and I \\add am\\add* not her husband."},{"style":"q1","verse":"","text":"Let her put away her whoring ⸤from before her⸥,\\f + \\fr 2:2 \\ft Literally “from her face” \\f*"},{"style":"q2","verse":"","text":"and her adultery from between her breasts."},{"style":"q1","verse":"","text":""},{"style":"v","verse":"3","text":"Lest I strip her naked"},{"style":"q2","verse":"","text":"and expose her like the day when she was born;"},{"style":"q1","verse":"","text":"I will make her like the desert"},{"style":"q2","verse":"","text":"and turn her into parched land;"},{"style":"q3","verse":"","text":"I will kill her with thirst."},{"style":"q1","verse":"","text":""},{"style":"v","verse":"4","text":"And I will not have pity on her children,"},{"style":"q2","verse":"","text":"because \\add they are\\add* children of whoredom."},{"style":"q3","verse":"","text":""},{"style":"v","verse":"5","text":"Because their mother was unfaithful;\\f + \\fr 2:5 \\ft Or “their mother played the whore” \\f*"},{"style":"q1","verse":"","text":"she who conceived them has acted shamefully,"},{"style":"q2","verse":"","text":"for she said:"},{"style":"q3","verse":"","text":"“I will go after my lovers,"},{"style":"q1","verse":"","text":"the ones who give \\add me\\add* my bread, my water,"},{"style":"q2","verse":"","text":"my wool, and my flax,"},{"style":"q3","verse":"","text":"my oil, and my drink.”"},{"style":"q1","verse":"","text":""},{"style":"v","verse":"6","text":"Therefore, Look!"},{"style":"q2","verse":"","text":"I \\add am\\add* going to hedge her path\\f + \\fr 2:6 \\ft Hebrew “your path” \\f* ⸤with thorns⸥,\\f + \\fr 2:6 \\ft Literally “with the thorns” \\f*"},{"style":"q3","verse":"","text":"and I will build a stone wall, a stone wall \\add against\\add* her,"},{"style":"q2","verse":"","text":"and she will not find her paths."},{"style":"q1","verse":"","text":""},{"style":"v","verse":"7","text":"Then she will pursue ⸤her lovers⸥,\\f + \\fr 2:7 \\ft Literally “the ones who love her” \\f*"},{"style":"q2","verse":"","text":"but she will not overtake them;"},{"style":"q3","verse":"","text":"she will seek them and not find \\add them\\add*;"},{"style":"q1","verse":"","text":"and she will say, “I will go"},{"style":"q2","verse":"","text":"and return to my first husband"},{"style":"q2","verse":"","text":"because \\add it was\\add* better for me then than now.”"},{"style":"q1","verse":"","text":""},{"style":"v","verse":"8","text":"But she did not know"},{"style":"q2","verse":"","text":"that \\add it was\\add* I who gave her"},{"style":"q3","verse":"","text":"grain, new wine, and oil,"},{"style":"q1","verse":"","text":"and who gave her silver in abundance,"},{"style":"q2","verse":"","text":"and gold which they made into a Baal."},{"style":"q1","verse":"","text":""},{"style":"v","verse":"9","text":"Therefore I will take again"},{"style":"q2","verse":"","text":"my grain in its time,"},{"style":"q3","verse":"","text":"and my wine in its season;"},{"style":"q1","verse":"","text":"and I will take away my wool and my flax,"},{"style":"q2","verse":"","text":"\\add which were\\add* to cover her nakedness."},{"style":"q1","verse":"","text":""},{"style":"v","verse":"10","text":"And now I will uncover her nakedness"},{"style":"q2","verse":"","text":"before the eyes of her lovers,"},{"style":"q3","verse":"","text":"and no one will rescue her from my hand."},{"style":"q1","verse":"","text":""},{"style":"v","verse":"11","text":"And I will put an end to all her mirth,"},{"style":"q2","verse":"","text":"her festivals,\\f + \\fr 2:11 \\ft Hebrew “festival” \\f* her new moons,\\f + \\fr 2:11 \\ft Hebrew “new moon” \\f* and her Sabbaths,\\f + \\fr 2:11 \\ft Hebrew “Sabbath” \\f*"},{"style":"q3","verse":"","text":"and all her appointed festivals;\\f + \\fr 2:11 \\ft Hebrew “festival” \\f*"},{"style":"q1","verse":"","text":""},{"style":"v","verse":"12","text":"and I will lay waste to her vines\\f + \\fr 2:12 \\ft Hebrew “vine” \\f* and her fig trees,\\f + \\fr 2:12 \\ft Hebrew “fig tree” \\f*"},{"style":"q2","verse":"","text":"of which she said,"},{"style":"q3","verse":"","text":"“They \\add are\\add* my payment for prostitution,"},{"style":"q2","verse":"","text":"which my lovers gave to me.”"},{"style":"q1","verse":"","text":"I will make them a forest,"},{"style":"q2","verse":"","text":"and the wild animals\\f + \\fr 2:12 \\ft Hebrew “animal” \\f* of the field will devour them."},{"style":"q1","verse":"","text":""},{"style":"v","verse":"13","text":"⸤I will punish her⸥\\f + \\fr 2:13 \\ft Literally “To visit sins upon her;” see 1:4 \\f* \\add for\\add* the days of the Baals,"},{"style":"q2","verse":"","text":"to whom she burns incense,"},{"style":"q1","verse":"","text":"and she decked herself \\add with\\add* her ornamental ring and jewelry,"},{"style":"q2","verse":"","text":"and she went after her lovers, and forgot me"},{"style":"q3","verse":"","text":"—a declaration of Yahweh."},{"style":"q1","verse":"","text":""},{"style":"v","verse":"14","text":"Therefore, Look! I \\add am\\add* going to allure her"},{"style":"q2","verse":"","text":"and bring her \\add into\\add* the desert,"},{"style":"q3","verse":"","text":"and ⸤I will speak tenderly to her⸥.\\f + \\fr 2:14 \\ft Literally “I will speak to her heart” \\f*"},{"style":"q1","verse":"","text":""},{"style":"v","verse":"15","text":"From there I will give her"},{"style":"q2","verse":"","text":"her vineyards,"},{"style":"q3","verse":"","text":"and the Valley of Achor as a doorway of hope."},{"style":"q1","verse":"","text":"And there she will respond,"},{"style":"q2","verse":"","text":"as \\add in\\add* the days of her youth,"},{"style":"q2","verse":"","text":"just as \\add in\\add* the day of her coming out of"},{"style":"q3","verse":"","text":"the land of Egypt."},{"style":"q1","verse":"","text":""},{"style":"v","verse":"16","text":"⸤And on that day⸥—\\f + \\fr 2:16 \\ft Literally, “And it will happen on that day” \\f*"},{"style":"q2","verse":"","text":"a declaration of Yahweh—"},{"style":"q3","verse":"","text":"you will call me, “My husband;”\\f + \\fr 2:16 \\ft Hebrew “Ishi” \\f*"},{"style":"q3","verse":"","text":"you will no longer call me, “My Baal.”\\f + \\fr 2:16 \\ft Hebrew “Baali” \\f*"},{"style":"q1","verse":"","text":""},{"style":"v","verse":"17","text":"I will remove the names"},{"style":"q2","verse":"","text":"of the Baals from her mouth,"},{"style":"q3","verse":"","text":"and they will no longer be mentioned by their name."},{"style":"q1","verse":"","text":""},{"style":"v","verse":"18","text":"I will make a covenant for them on that day,"},{"style":"q2","verse":"","text":"with the animals\\f + \\fr 2:18 \\ft Hebrew “animal” \\f* of the field,"},{"style":"q2","verse":"","text":"with the birds\\f + \\fr 2:18 \\ft Hebrew “bird” \\f* of the heaven, and"},{"style":"q2","verse":"","text":"\\add with\\add* the creeping things\\f + \\fr 2:18 \\ft Hebrew “creeping thing” \\f* of the ground;"},{"style":"q3","verse":"","text":"\\add the\\add* bow, \\add the\\add* sword, and \\add the\\add* war I will abolish from the land, and I will let them lie down in safety."},{"style":"q1","verse":"","text":""},{"style":"v","verse":"19","text":"And I will take you as my wife forever;"},{"style":"q2","verse":"","text":"I will take you as a wife for myself in righteousness and in justice,"},{"style":"q3","verse":"","text":"in steadfast love and in mercy."},{"style":"q1","verse":"","text":""},{"style":"v","verse":"20","text":"⸤I will take you as my wife⸥\\f + \\fr 2:20 \\ft Literally “I will take you as a wife to me” \\f* in faithfulness,"},{"style":"q2","verse":"","text":"and you will know Yahweh."},{"style":"q1","verse":"","text":""},{"style":"v","verse":"21","text":"On that day I will answer, ⸤declares Yahweh⸥,\\f + \\fr 2:21 \\ft Literally “a declaration of Yahweh \\f*"},{"style":"q2","verse":"","text":"I will answer the heavens,"},{"style":"q3","verse":"","text":"and they will answer the earth."},{"style":"q1","verse":"","text":""},{"style":"v","verse":"22","text":"And the earth will answer"},{"style":"q2","verse":"","text":"the grain, the wine, and the oil,"},{"style":"q1","verse":"","text":"and they will answer Jezreel.\\f + \\fr 2:22 \\ft Jezreel means “God sows” \\f*"},{"style":"q2","verse":"","text":""},{"style":"v","verse":"23","text":"I will sow her for myself in the land;"},{"style":"q3","verse":"","text":"I will have pity on Lo-ruhama;\\f + \\fr 2:23 \\ft Lo-ruhama means “Not pitied” \\f*"},{"style":"q2","verse":"","text":"I will say to Lo-ammi,\\f + \\fr 2:23 \\ft Lo-ammi means “Not my people” \\f*"},{"style":"q3","verse":"","text":"“You are my people,”"},{"style":"q2","verse":"","text":"and he himself will say, “\\add you are\\add* my God.”"},{"style":"sd0","verse":"","text":""}]