[{"style":"cl","verse":"","text":"Psalm 97"},{"style":"s1","verse":"","text":"Yahweh’s Glorious Reign"},{"style":"q1","verse":"","text":""},{"style":"v","verse":"1","text":"Yahweh is king! Let the earth rejoice;"},{"style":"q1","verse":"","text":"let many coastlands be glad."},{"style":"q1","verse":"","text":""},{"style":"v","verse":"2","text":"Cloud and thick darkness \\add are\\add* surrounding him;"},{"style":"q1","verse":"","text":"righteousness and justice \\add are\\add* the foundation of his throne."},{"style":"q1","verse":"","text":""},{"style":"v","verse":"3","text":"Fire goes before him,"},{"style":"q1","verse":"","text":"and devours his enemies round about."},{"style":"q1","verse":"","text":""},{"style":"v","verse":"4","text":"His lightnings light \\add the\\add* world;"},{"style":"q1","verse":"","text":"the earth sees and trembles."},{"style":"q1","verse":"","text":""},{"style":"v","verse":"5","text":"\\add The\\add* mountains melt like wax at the presence of Yahweh,"},{"style":"q1","verse":"","text":"at the presence of the Lord of all the earth."},{"style":"q1","verse":"","text":""},{"style":"v","verse":"6","text":"The heavens declare his righteousness,"},{"style":"q1","verse":"","text":"and all the peoples see his glory."},{"style":"q1","verse":"","text":""},{"style":"v","verse":"7","text":"Let all who serve an image be ashamed,"},{"style":"q1","verse":"","text":"those who boast about idols.\\f + \\fr 97:7 \\ft This word for idols suggests something worthless or insignificant \\f*"},{"style":"q1","verse":"","text":"Worship him, all you gods."},{"style":"q1","verse":"","text":""},{"style":"v","verse":"8","text":"Zion hears and is glad,"},{"style":"q1","verse":"","text":"and the daughters of Judah rejoice"},{"style":"q1","verse":"","text":"because of your judgments, O Yahweh."},{"style":"q1","verse":"","text":""},{"style":"v","verse":"9","text":"For you, O Yahweh, \\add are\\add* most high over all the earth."},{"style":"q1","verse":"","text":"You are highly\\f + \\fr 97:9 \\ft Hebrew “very” \\f* exalted above all gods."},{"style":"q1","verse":"","text":""},{"style":"v","verse":"10","text":"You who love Yahweh, hate evil."},{"style":"q1","verse":"","text":"He protects the lives of his faithful;"},{"style":"q1","verse":"","text":"he delivers them from \\add the\\add* hand of \\add the\\add* wicked."},{"style":"q1","verse":"","text":""},{"style":"v","verse":"11","text":"Light \\add is\\add* sown for the righteous,"},{"style":"q1","verse":"","text":"and joy for \\add the\\add* upright in heart."},{"style":"q1","verse":"","text":""},{"style":"v","verse":"12","text":"Be glad in Yahweh, \\add you\\add* righteous,"},{"style":"q1","verse":"","text":"and give thanks ⸤to his holy name⸥.\\f + \\fr 97:12 \\ft Literally “to his holy remembrance” or “to his memorable holiness” \\f*"}]