[{"style":"s1","verse":"","text":"Les crimes d’Israël et de Juda; censures et menaces"},{"style":"r","verse":"","text":"V. 1-5: cf. Jé 5:1-9; 9:2-10."},{"style":"q1","verse":"","text":""},{"style":"v","verse":"1","text":"Écoutez la parole de l’Éternel, enfants d’Israël!"},{"style":"q1","verse":"","text":"Car l’Éternel a un \\x a \\xo 4.1 \\xt Mi 6:2.\\x*procès avec les habitants du pays,"},{"style":"q1","verse":"","text":"Parce qu’il n’y a point de vérité, point de miséricorde,"},{"style":"q1","verse":"","text":"Point de connaissance de Dieu dans le pays."},{"style":"q1","verse":"","text":""},{"style":"v","verse":"2","text":"Il n’y a que parjures et mensonges,"},{"style":"q1","verse":"","text":"Assassinats, vols et adultères;"},{"style":"q1","verse":"","text":"On use de violence, on commet meurtre sur meurtre."},{"style":"q1","verse":"","text":""},{"style":"v","verse":"3","text":"C’est pourquoi le pays sera dans le deuil,"},{"style":"q1","verse":"","text":"Tous ceux qui l’habitent seront languissants,"},{"style":"q1","verse":"","text":"Et avec eux les bêtes des champs et les oiseaux du ciel;"},{"style":"q1","verse":"","text":"Même les poissons de la mer disparaîtront."},{"style":"q1","verse":"","text":""},{"style":"v","verse":"4","text":"Mais que nul ne conteste, que nul ne se livre aux reproches;"},{"style":"q1","verse":"","text":"Car ton peuple est comme ceux qui disputent avec les sacrificateurs."},{"style":"q1","verse":"","text":""},{"style":"v","verse":"5","text":"Tu tomberas de jour,"},{"style":"q1","verse":"","text":"Le prophète avec toi tombera de nuit,"},{"style":"q1","verse":"","text":"Et je détruirai ta mère."},{"style":"r","verse":"","text":"V. 6-10: cf. Jé 8:8-13. Mal 2:1-9."},{"style":"q1","verse":"","text":""},{"style":"v","verse":"6","text":"Mon peuple est détruit, parce qu’il lui manque la connaissance."},{"style":"q1","verse":"","text":"Puisque tu as rejeté la connaissance,"},{"style":"q1","verse":"","text":"Je te rejetterai, et tu seras dépouillé de mon sacerdoce;"},{"style":"q1","verse":"","text":"Puisque tu as oublié la loi de ton Dieu,"},{"style":"q1","verse":"","text":"J’oublierai aussi tes enfants."},{"style":"q1","verse":"","text":""},{"style":"v","verse":"7","text":"Plus ils se sont multipliés, plus ils ont péché contre moi:"},{"style":"q1","verse":"","text":"Je changerai leur gloire en ignominie."},{"style":"q1","verse":"","text":""},{"style":"v","verse":"8","text":"Ils se repaissent des péchés de mon peuple,"},{"style":"q1","verse":"","text":"Ils sont avides de ses iniquités."},{"style":"q1","verse":"","text":""},{"style":"v","verse":"9","text":"Il en sera du sacrificateur \\x b \\xo 4.9 \\xt És 24:2.\\x*comme du peuple;"},{"style":"q1","verse":"","text":"Je le châtierai selon ses voies,"},{"style":"q1","verse":"","text":"Je lui rendrai selon ses œuvres."},{"style":"q1","verse":"","text":""},{"style":"v","verse":"10","text":"\\x c \\xo 4.10 \\xt Mi 6:14.\\x*Ils mangeront sans se rassasier,"},{"style":"q1","verse":"","text":"Ils se prostitueront sans multiplier,"},{"style":"q1","verse":"","text":"Parce qu’ils ont abandonné l’Éternel et ses commandements."},{"style":"r","verse":"","text":"V. 11-14: cf. No 25:1-3. Éz 20:27-33."},{"style":"q1","verse":"","text":""},{"style":"v","verse":"11","text":"La prostitution, le vin et le moût, font perdre le sens."},{"style":"q1","verse":"","text":""},{"style":"v","verse":"12","text":"Mon peuple consulte son bois,"},{"style":"q1","verse":"","text":"Et c’est son bâton qui lui parle;"},{"style":"q1","verse":"","text":"Car \\x d \\xo 4.12 \\xt Os 5:4.\\x*l’esprit de prostitution égare,"},{"style":"q1","verse":"","text":"Et ils se prostituent loin de leur Dieu."},{"style":"q1","verse":"","text":""},{"style":"v","verse":"13","text":"Ils sacrifient sur le sommet des \\x e \\xo 4.13 \\xt És 57:7.\\x*montagnes,"},{"style":"q1","verse":"","text":"Ils brûlent de l’encens sur les \\x f \\xo 4.13 \\xt Éz 20:28.\\x*collines,"},{"style":"q1","verse":"","text":"Sous les chênes, les peupliers, les \\x g \\xo 4.13 \\xt És 1:29.\\x*térébinthes,"},{"style":"q1","verse":"","text":"Dont l’ombrage est agréable."},{"style":"q1","verse":"","text":"C’est pourquoi vos filles se prostituent,"},{"style":"q1","verse":"","text":"Et vos belles-filles sont adultères."},{"style":"q1","verse":"","text":""},{"style":"v","verse":"14","text":"Je ne punirai pas vos filles parce qu’elles se prostituent,"},{"style":"q1","verse":"","text":"Ni vos belles-filles parce qu’elles sont adultères,"},{"style":"q1","verse":"","text":"Car eux-mêmes vont à l’écart avec des prostituées,"},{"style":"q1","verse":"","text":"Et sacrifient avec des femmes débauchées."},{"style":"q1","verse":"","text":"Le peuple insensé court à sa perte."},{"style":"r","verse":"","text":"V. 15-19: cf. Os 12:1; 10:1-8."},{"style":"q1","verse":"","text":""},{"style":"v","verse":"15","text":"Si tu te livres à la prostitution, ô Israël,"},{"style":"q1","verse":"","text":"Que Juda ne se rende pas coupable;"},{"style":"q1","verse":"","text":"N’allez pas à Guilgal, ne montez pas à Beth-Aven,"},{"style":"q1","verse":"","text":"Et ne jurez pas: L’Éternel est vivant!"},{"style":"q1","verse":"","text":""},{"style":"v","verse":"16","text":"Parce qu’Israël se révolte comme une génisse indomptable,"},{"style":"q1","verse":"","text":"Maintenant l’Éternel le fera paître"},{"style":"q1","verse":"","text":"Comme un agneau dans de vastes plaines."},{"style":"q1","verse":"","text":""},{"style":"v","verse":"17","text":"Éphraïm est attaché aux idoles: laisse-le!"},{"style":"q1","verse":"","text":""},{"style":"v","verse":"18","text":"A peine ont-ils cessé de boire"},{"style":"q1","verse":"","text":"Qu’ils se livrent à la prostitution;"},{"style":"q1","verse":"","text":"Leurs chefs sont avides d’ignominie."},{"style":"q1","verse":"","text":""},{"style":"v","verse":"19","text":"Le vent les enveloppera de ses ailes,"},{"style":"q1","verse":"","text":"Et ils auront honte de leurs sacrifices."}]