[{"style":"s1","text":"The Doom of the Wicked City is Certain"},{"style":"sd0","text":""},{"style":"q1","text":""},{"style":"v","text":"Woe to the city \\add that has shed\\add* ⸤much blood⸥!\\f + \\fr 3:1 \\ft Literally “bloods” \\f*"},{"style":"q2","text":"⸤She is a deceiver⸥,\\f + \\fr 3:1 \\ft Literally “All of her \\fq is \\ft deception” \\f*"},{"style":"q1","text":"She is filled \\add with\\add* plunder,"},{"style":"q2","text":"⸤She has hoarded her spoils of war⸥.\\f + \\fr 3:1 \\ft Literally “Prey does not depart” \\f*"},{"style":"q1","text":""},{"style":"v","text":"The crack of the whip!"},{"style":"q2","text":"The rumbling of the \\add chariot\\add* wheel!"},{"style":"q1","text":"The galloping of the horse!"},{"style":"q2","text":"The racing of the chariot!"},{"style":"q1","text":""},{"style":"v","text":"Chariots charge!"},{"style":"q2","text":"Swords flash!"},{"style":"q3","text":"Spears glitter!"},{"style":"q1","text":"⸤Many corpses are piled high⸥!\\f + \\fr 3:3 \\ft Literally “Many dead, piles of corpses” \\f*"},{"style":"q2","text":"There is no end to the slain!"},{"style":"q3","text":"They stumble over their dead!"},{"style":"sd0","text":""},{"style":"s1","text":"Harlot Nineveh Will Get What She Deserves"},{"style":"sd0","text":""},{"style":"q1","text":""},{"style":"v","text":"“Because of the many idolatries of \\add the\\add* prostitute,"},{"style":"q2","text":"the beautiful charm \\add of\\add* a mistress of witchcraft,"},{"style":"q1","text":"she who enslaves nations by her harlotries,"},{"style":"q2","text":"and peoples by her sorceries,"},{"style":"q1","text":""},{"style":"v","text":"“Look! I am against you!” ⸤declares⸥\\f + \\fr 3:5 \\ft Literally “a declaration of” \\f*Yahweh."},{"style":"q2","text":"“I will strip up your skirts over your face;"},{"style":"q3","text":"I will let nations look \\add at\\add* your nakedness and your shame."},{"style":"q1","text":""},{"style":"v","text":"“I will throw filth upon you,"},{"style":"q2","text":"I will treat you with contempt,"},{"style":"q3","text":"I will make you a spectacle."},{"style":"q1","text":""},{"style":"v","text":"“And it will be that everyone who sees you will flee from you,"},{"style":"q2","text":"And ⸤they⸥\\f + \\fr 3:7 \\ft Hebrew “he” \\f* will say, ‘Nineveh is destroyed!’"},{"style":"q1","text":"Who will mourn for her?"},{"style":"q2","text":"From whence shall I seek comforters for you?”"},{"style":"sd0","text":""},{"style":"s1","text":"Nineveh Will Suffer the Same Fate She Inflicted on Thebes"},{"style":"sd0","text":""},{"style":"q1","text":""},{"style":"v","text":"Are you better than Thebes?\\f + \\fr 3:8 \\ft Hebrew “No-Amon” \\f*"},{"style":"q2","text":"She who sits at the Nile, surrounded by her waters,"},{"style":"q1","text":"her rampart \\add was the\\add* sea and water \\add was\\add* her wall."},{"style":"q1","text":""},{"style":"v","text":"Cush \\add was\\add* her strength, Egypt without end;"},{"style":"q2","text":"Put and Libya were among ⸤your allies⸥.\\f + \\fr 3:9 \\ft Literally “your helpers” \\f*"},{"style":"q1","text":""},{"style":"v","text":"Yet she went into captivity as an exile;"},{"style":"q2","text":"her children were dashed to pieces at the head of \\add the\\add* streets;"},{"style":"q1","text":"they cast lots for all of her nobles;"},{"style":"q2","text":"all of her dignitaries were bound with chains."},{"style":"q1","text":""},{"style":"v","text":"You also will behave like a drunkard;"},{"style":"q2","text":"You also will hide yourself;"},{"style":"q3","text":"You also will seek refuge from \\add the\\add* enemy."},{"style":"sd0","text":""},{"style":"s1","text":"Nineveh’s Defenses Will Fail"},{"style":"sd0","text":""},{"style":"q1","text":""},{"style":"v","text":"All of your fortifications \\add are like\\add* fig trees with \\add ripe\\add* firstfruits—"},{"style":"q2","text":"if they are shaken, they will fall into the mouth of the eater."},{"style":"q1","text":""},{"style":"v","text":"Look! Your troops \\add are like\\add* women in your midst."},{"style":"q2","text":"The gates of your land are wide open to your enemies;"},{"style":"q3","text":"fire will consume the bars \\add of your gates\\add*."},{"style":"q1","text":""},{"style":"v","text":"Draw water for a siege!"},{"style":"q2","text":"Strengthen your fortifications!"},{"style":"q1","text":"Go to the mud \\add pit\\add*!"},{"style":"q2","text":"Trample the clay!"},{"style":"q3","text":"Grasp the brick mold!"},{"style":"q1","text":""},{"style":"v","text":"There fire will consume you;"},{"style":"q2","text":"the sword will cut you off."},{"style":"q3","text":"It will consume you like the locust."},{"style":"sd0","text":""},{"style":"s1","text":"Nineveh’s Defenders Will Flee"},{"style":"sd0","text":""},{"style":"q1","text":"Multiply yourself like the locust!"},{"style":"q2","text":"Multiply yourself like the grasshopper!"},{"style":"q1","text":""},{"style":"v","text":"You have increased your merchants more than the stars of heaven;"},{"style":"q2","text":"\\add like\\add* the locust they will shed \\add their skin\\add* and fly away."},{"style":"q1","text":""},{"style":"v","text":"Your officials \\add are\\add* like locusts;"},{"style":"q2","text":"your commanders \\add are\\add* like a swarm of locusts."},{"style":"q1","text":"They encamp on the walls on a cold day;"},{"style":"q2","text":"when the sun rises, they fly away—"},{"style":"q3","text":"no one knows where they have gone."},{"style":"sd0","text":""},{"style":"s1","text":"Nineveh Will Come to an End"},{"style":"sd0","text":""},{"style":"q1","text":""},{"style":"v","text":"Your shepherds are sleeping, \\add O\\add* king of Assyria!"},{"style":"q2","text":"Your nobles slumber."},{"style":"q1","text":"Your people are scattered on the mountains;"},{"style":"q2","text":"no one can gather them."},{"style":"q1","text":""},{"style":"v","text":"There is no healing for your wound;"},{"style":"q2","text":"your injury is fatal."},{"style":"q1","text":"All who hear the report of you will clap \\add their\\add* hands \\add for joy\\add* concerning you,"},{"style":"q2","text":"⸤For who has not suffered at the hands of your endless cruelty⸥?\\f + \\fr 3:19 \\ft Literally “For over whom has your endless cruelty not passed?” \\f*"},{"style":"sd0","text":""}]