[{"style":"sd0","verse":"","text":""},{"style":"q1","verse":"","text":""},{"style":"v","verse":"1","text":"Balances of deceit \\add are\\add* an abomination of Yahweh,"},{"style":"q2","verse":"","text":"but ⸤an accurate weight⸥\\f + \\fr 11:1 \\ft Literally “a full stone” or “a pure stone” \\f* delights him."},{"style":"q1","verse":"","text":""},{"style":"v","verse":"2","text":"Pride comes, then disgrace comes,"},{"style":"q2","verse":"","text":"but wisdom \\add is\\add* with the humble."},{"style":"q1","verse":"","text":""},{"style":"v","verse":"3","text":"The integrity of the upright guides them,"},{"style":"q2","verse":"","text":"but the crookedness of the treacherous destroys them."},{"style":"q1","verse":"","text":""},{"style":"v","verse":"4","text":"Wealth does not profit on the day of wrath,"},{"style":"q2","verse":"","text":"but righteousness will deliver from death."},{"style":"q1","verse":"","text":""},{"style":"v","verse":"5","text":"The righteousness of the blameless will keep his ways straight,"},{"style":"q2","verse":"","text":"but the wicked will fall by his wickedness."},{"style":"q1","verse":"","text":""},{"style":"v","verse":"6","text":"The righteousness of the upright will save them,"},{"style":"q2","verse":"","text":"but by a scheme the treacherous will be taken captive."},{"style":"q1","verse":"","text":""},{"style":"v","verse":"7","text":"With the death of a wicked person, hope will die,"},{"style":"q2","verse":"","text":"and the expectation of the godless perishes."},{"style":"q1","verse":"","text":""},{"style":"v","verse":"8","text":"The righteous is delivered from trouble,"},{"style":"q2","verse":"","text":"but the wicked enters into it."},{"style":"q1","verse":"","text":""},{"style":"v","verse":"9","text":"With a mouth, the godless shall destroy his neighbor,"},{"style":"q2","verse":"","text":"but by knowledge the righteous are delivered."},{"style":"q1","verse":"","text":""},{"style":"v","verse":"10","text":"When good \\add is with\\add* the righteous, \\add the\\add* city rejoices,"},{"style":"q2","verse":"","text":"and with the perishing of the wicked, jubilation."},{"style":"q1","verse":"","text":""},{"style":"v","verse":"11","text":"By the blessing of the upright, a city will be exalted,"},{"style":"q2","verse":"","text":"but by the mouth of the wicked, it will be overthrown."},{"style":"q1","verse":"","text":""},{"style":"v","verse":"12","text":"He who lacks ⸤sense⸥\\f + \\fr 11:12 \\ft Literally “heart” \\f* belittles his neighbor,"},{"style":"q2","verse":"","text":"but a person of intelligence will remain silent."},{"style":"q1","verse":"","text":""},{"style":"v","verse":"13","text":"A gossip walks \\add about\\add* telling a secret,"},{"style":"q2","verse":"","text":"but the trustworthy in spirit keeps \\add the\\add* matter."},{"style":"q1","verse":"","text":""},{"style":"v","verse":"14","text":"Where there is no guidance, a nation\\f + \\fr 11:14 \\ft Or “people” \\f* shall fall,"},{"style":"q2","verse":"","text":"but \\add there is\\add* safety in an abundance of counsel."},{"style":"q1","verse":"","text":""},{"style":"v","verse":"15","text":"He will suffer trouble when he loans to a stranger,"},{"style":"q2","verse":"","text":"but he who refuses a pledge is safe."},{"style":"q1","verse":"","text":""},{"style":"v","verse":"16","text":"A woman of grace receives honor,"},{"style":"q2","verse":"","text":"but the ruthless gets wealth."},{"style":"q1","verse":"","text":""},{"style":"v","verse":"17","text":"A person of kindness rewards himself,\\f + \\fr 11:17 \\ft Or “soul,” or “inner self” \\f*"},{"style":"q2","verse":"","text":"but a cruel \\add person\\add* harms his own flesh."},{"style":"q1","verse":"","text":""},{"style":"v","verse":"18","text":"The wicked earns\\f + \\fr 11:18 \\ft Or “does, makes” \\f* ⸤deceptive gain⸥,\\f + \\fr 11:18 \\ft Literally “gain of deception” \\f*"},{"style":"q2","verse":"","text":"but he who sows righteousness, a ⸤true reward⸥.\\f + \\fr 11:18 \\ft Literally “a reward of truth” \\f*"},{"style":"q1","verse":"","text":""},{"style":"v","verse":"19","text":"He who is steadfast in righteousness \\add is\\add* to life"},{"style":"q2","verse":"","text":"as\\f + \\fr 11:19 \\ft Hebrew “and” \\f* he who pursues evil \\add is\\add* to death."},{"style":"q1","verse":"","text":""},{"style":"v","verse":"20","text":"An abomination of Yahweh \\add are\\add* the ⸤crooked of heart⸥,\\f + \\fr 11:20 \\ft Literally “crooked ones of heart”; “heart” may also be translated “mind” \\f*"},{"style":"q2","verse":"","text":"but his delight \\add are\\add* ⸤those with blameless ways⸥.\\f + \\fr 11:20 \\ft Literally “blameless ones of ways” \\f*"},{"style":"q1","verse":"","text":""},{"style":"v","verse":"21","text":"⸤Rest assured⸥,\\f + \\fr 11:21 \\ft Literally “Hand to hand” \\f* the wicked will not go unpunished,"},{"style":"q2","verse":"","text":"but the offspring\\f + \\fr 11:21 \\ft Or “seed” \\f* of the righteous will escape."},{"style":"q1","verse":"","text":""},{"style":"v","verse":"22","text":"A ring of gold in \\add the\\add* snout of a pig"},{"style":"q2","verse":"","text":"\\add is\\add* a woman \\add who is\\add* beautiful but without discretion."},{"style":"q1","verse":"","text":""},{"style":"v","verse":"23","text":"The desire of the righteous \\add is\\add* only good,"},{"style":"q2","verse":"","text":"but the expectation of the wicked, wrath."},{"style":"q1","verse":"","text":""},{"style":"v","verse":"24","text":"There is one who gives yet ⸤grows richer⸥,\\f + \\fr 11:24 \\ft Literally “adding more” \\f*"},{"style":"q2","verse":"","text":"but he who withholds ⸤what is right⸥\\f + \\fr 11:24 \\ft Literally “from what is right” \\f* only \\add finds\\add* need."},{"style":"q1","verse":"","text":""},{"style":"v","verse":"25","text":"A person of blessing will be enriched,"},{"style":"q2","verse":"","text":"and he who gives water also will be refreshed."},{"style":"q1","verse":"","text":""},{"style":"v","verse":"26","text":"He who withholds grain, the people curse him,"},{"style":"q2","verse":"","text":"but a blessing \\add is\\add* for the head of him who sells."},{"style":"q1","verse":"","text":""},{"style":"v","verse":"27","text":"He who diligently seeks good seeks favor,"},{"style":"q2","verse":"","text":"but he who inquires of evil, it will come to him."},{"style":"q1","verse":"","text":""},{"style":"v","verse":"28","text":"He who trusts in his wealth \\add is\\add* he who will fall,"},{"style":"q2","verse":"","text":"but like a green leaf the righteous will flourish."},{"style":"q1","verse":"","text":""},{"style":"v","verse":"29","text":"He who brings trouble \\add to\\add* his household, he will inherit wind,\\f + \\fr 11:29 \\ft Or “breath, spirit” \\f*"},{"style":"q2","verse":"","text":"and a fool will serve the wise of heart."},{"style":"q1","verse":"","text":""},{"style":"v","verse":"30","text":"The fruit of righteousness is a tree of life,"},{"style":"q2","verse":"","text":"and he who captures souls\\f + \\fr 11:30 \\ft Or “persons,” or “inner selves” \\f* \\add is\\add* wise."},{"style":"q1","verse":"","text":""},{"style":"v","verse":"31","text":"If the righteous on earth will be repaid,"},{"style":"q2","verse":"","text":"⸤how much more⸥\\f + \\fr 11:31 \\ft Literally “more for” \\f* the wicked and sinner."},{"style":"sd0","verse":"","text":""}]