[{"style":"s1","text":"Wisdom Calls"},{"style":"sd0","text":""},{"style":"q1","text":""},{"style":"v","text":"Does not wisdom call,"},{"style":"q2","text":"and understanding raise its voice?"},{"style":"q1","text":""},{"style":"v","text":"⸤Atop the heights⸥\\f + \\fr 8:2 \\ft Literally “At a head of the heights” \\f* beside the road,"},{"style":"q2","text":"at the crossroads she stands."},{"style":"q1","text":""},{"style":"v","text":"Beside gates, before towns,"},{"style":"q2","text":"\\add at the\\add* entrance of doors, she cries out:"},{"style":"q1","text":""},{"style":"v","text":"“To you, O ⸤people⸥,\\f + \\fr 8:4 \\ft Literally “men” \\f* I call,"},{"style":"q2","text":"and my cry is to the children of humankind."},{"style":"q1","text":""},{"style":"v","text":"Learn prudence, O simple ones;"},{"style":"q2","text":"fools, learn ⸤intelligence⸥.\\f + \\fr 8:5 \\ft Literally “heart” \\f*"},{"style":"q1","text":""},{"style":"v","text":"Listen! For noble things I will speak,"},{"style":"q2","text":"and upright things from the opening of my lips."},{"style":"q1","text":""},{"style":"v","text":"My mouth will utter truth,"},{"style":"q2","text":"and wickedness \\add is\\add* an abomination to my lips."},{"style":"q1","text":""},{"style":"v","text":"All sayings of my mouth \\add are\\add* in righteousness;"},{"style":"q2","text":"none of them are twisted and crooked."},{"style":"q1","text":""},{"style":"v","text":"All of them are straight to him who understands,"},{"style":"q2","text":"and upright to those who find knowledge."},{"style":"q1","text":""},{"style":"v","text":"Take my teaching and not silver;"},{"style":"q2","text":"may you choose knowledge rather than choice gold."},{"style":"q1","text":""},{"style":"v","text":"For wisdom is better than jewels,"},{"style":"q2","text":"and all desires shall not compare with her."},{"style":"q1","text":""},{"style":"v","text":"I, wisdom, live with prudence,"},{"style":"q2","text":"and I find knowledge and discretion."},{"style":"q1","text":""},{"style":"v","text":"The fear of Yahweh \\add is\\add* hatred of evil,"},{"style":"q2","text":"pride, and arrogance and an evil way."},{"style":"q2","text":"And I hate a mouth of perversity."},{"style":"q1","text":""},{"style":"v","text":"⸤Advice and sound judgment⸥\\f + \\fr 8:14 \\ft Literally “To/for me are advice and sound judgment” \\f* are mine;"},{"style":"q2","text":"I am understanding, ⸤strength is mine⸥.\\f + \\fr 8:14 \\ft Literally “to/for me is strength” \\f*"},{"style":"q1","text":""},{"style":"v","text":"By me kings reign,"},{"style":"q2","text":"and rulers decree righteousness."},{"style":"q1","text":""},{"style":"v","text":"By me rulers rule,"},{"style":"q2","text":"and nobles—all judges of righteousness."},{"style":"q1","text":""},{"style":"v","text":"I love ⸤those who love me⸥,\\f + \\fr 8:17 \\ft Literally “her lovers” \\f*"},{"style":"q2","text":"and those who seek me diligently shall find me."},{"style":"q1","text":""},{"style":"v","text":"Fortune and glory \\add are\\add* with me,"},{"style":"q2","text":"enduring wealth and righteousness."},{"style":"q1","text":""},{"style":"v","text":"My fruit is better than gold,\\f + \\fr 8:19 \\ft Literally “fine gold” \\f* even refined gold,"},{"style":"q2","text":"and my yield than choice silver."},{"style":"q1","text":""},{"style":"v","text":"In the way of righteousness I walk,"},{"style":"q2","text":"in the midst of paths of justice,"},{"style":"q1","text":""},{"style":"v","text":"\\add in order\\add* to endow those who love me \\add with\\add* wealth,"},{"style":"q2","text":"and I will fill their treasuries."},{"style":"sd0","text":""},{"style":"s1","text":"Wisdom at Creation"},{"style":"sd0","text":""},{"style":"q1","text":""},{"style":"v","text":"“Yahweh possessed\\f + \\fr 8:22 \\ft Or “gained,” or “acquired” \\f* me, \\add the\\add* first of his ways,"},{"style":"q2","text":"before his acts ⸤of old⸥.\\f + \\fr 8:22 \\ft Literally “from before” or “from then” \\f*"},{"style":"q1","text":""},{"style":"v","text":"From eternity, I was set up from \\add the\\add* first,"},{"style":"q2","text":"from the beginning\\f + \\fr 8:23 \\ft Hebrew “beginnings” \\f* of the earth."},{"style":"q1","text":""},{"style":"v","text":"When there were no depths, I was brought forth,"},{"style":"q2","text":"when there were no springs of ⸤abounding⸥\\f + \\fr 8:24 \\ft Literally “made heavy” \\f* water."},{"style":"q1","text":""},{"style":"v","text":"Before mountains had been shaped,"},{"style":"q2","text":"before hills, I was brought forth."},{"style":"q1","text":""},{"style":"v","text":"When he had not yet made earth and fields,"},{"style":"q2","text":"or the first dust of the world,"},{"style":"q1","text":""},{"style":"v","text":"⸤when he established⸥\\f + \\fr 8:27 \\ft Literally “in his establishing” \\f* the heavens, there I \\add was\\add*,"},{"style":"q2","text":"⸤when he drew⸥\\f + \\fr 8:27 \\ft Literally “in his drawing” \\f* a circle upon the face of the deep,"},{"style":"q1","text":""},{"style":"v","text":"⸤when he made⸥\\f + \\fr 8:28 \\ft Literally “in his making” \\f* skies from above,"},{"style":"q2","text":"when he founded fountains of the deep,"},{"style":"q1","text":""},{"style":"v","text":"⸤when he assigned⸥\\f + \\fr 8:29 \\ft Literally “in his assigning” \\f* his limits to the sea,"},{"style":"q2","text":"that waters shall not transgress his ⸤command⸥,\\f + \\fr 8:29 \\ft Literally “mouth” \\f*"},{"style":"q2","text":"⸤when he marked⸥\\f + \\fr 8:29 \\ft Literally “in his marking” \\f* the foundations of the earth,"},{"style":"q1","text":""},{"style":"v","text":"I was ⸤beside⸥\\f + \\fr 8:30 \\ft Literally “at the place of” \\f* him, a master workman,"},{"style":"q2","text":"and I was delighting day by day,"},{"style":"q2","text":"rejoicing before him ⸤always⸥,\\f + \\fr 8:30 \\ft Literally “in all \\fq of \\ft time” \\f*"},{"style":"q1","text":""},{"style":"v","text":"rejoicing in the world of his earth,"},{"style":"q2","text":"and my delight \\add was\\add* with the children of humankind."},{"style":"sd0","text":""},{"style":"s1","text":"Benefits of Following Wisdom"},{"style":"sd0","text":""},{"style":"q1","text":""},{"style":"v","text":"“And now, children, listen to me;"},{"style":"q2","text":"happy \\add are\\add* those who will keep my ways."},{"style":"q1","text":""},{"style":"v","text":"Hear teaching and be wise;"},{"style":"q2","text":"do not neglect \\add it\\add*."},{"style":"q1","text":""},{"style":"v","text":"Happy \\add is the\\add* person who listens to me,"},{"style":"q2","text":"\\add in order\\add* to keep watch at my doors day by day,"},{"style":"q2","text":"\\add in order\\add* to guard the frames of my entrances."},{"style":"q1","text":""},{"style":"v","text":"For he who finds me \\add is\\add* he who finds\\f + \\fr 8:35 \\ft Hebrew “those who find” \\f* life,"},{"style":"q2","text":"and he obtains favor from Yahweh."},{"style":"q1","text":""},{"style":"v","text":"But he who misses me injures himself.\\f + \\fr 8:36 \\ft Or “soul,” or “inner self” \\f*"},{"style":"q2","text":"All those who hate me love death.”"},{"style":"sd0","text":""}]