[{"style":"s1","text":"Elihu Asserts God’s Justice"},{"style":"m","text":""},{"style":"v","text":"Thus\\f + \\fr 34:1 \\ft Hebrew “And” \\f* Elihu ⸤spoke up⸥\\f + \\fr 34:1 \\ft Literally “answered”; see NET \\f* and said,"},{"style":"sd0","text":""},{"style":"q1","text":""},{"style":"v","text":"“Hear my words, you wise men,"},{"style":"q1","text":"and listen to me, you who know,"},{"style":"q1","text":""},{"style":"v","text":"for \\add the\\add* ear tests words,"},{"style":"q1","text":"and \\add the\\add* palate tastes ⸤food⸥.\\f + \\fr 34:3 \\ft Literally “to eat” \\f*"},{"style":"q1","text":""},{"style":"v","text":"Let us choose justice for ourselves;"},{"style":"q1","text":"let us determine among ourselves what \\add is\\add* good—"},{"style":"q1","text":""},{"style":"v","text":"for Job has said, ‘I am righteous,"},{"style":"q1","text":"but God has taken away my justice."},{"style":"q1","text":""},{"style":"v","text":"Should I lie concerning my justice?"},{"style":"q1","text":"\\add Though I am\\add* without transgression, my wound caused by an arrow is incurable.’"},{"style":"q1","text":""},{"style":"v","text":"What man \\add is\\add* like Job,"},{"style":"q1","text":"who drinks scorn like water?"},{"style":"q1","text":""},{"style":"v","text":"And he goes on the road in company with instigators of mischief,"},{"style":"q1","text":"and walks with men of wickedness."},{"style":"q1","text":""},{"style":"v","text":"Indeed, he says, ‘A man does not profit"},{"style":"q1","text":"when he takes delight in God.’"},{"style":"q1","text":""},{"style":"v","text":"“Therefore, listen to me, ⸤people who have sense⸥:\\f + \\fr 34:10 \\ft Literally “men of heart” \\f*"},{"style":"q1","text":"far be it from God ⸤that he should commit wickedness⸥\\f + \\fr 34:10 \\ft Literally “from wickedness” \\f*"},{"style":"q1","text":"and that Shaddai ⸤should do wrong⸥.\\f + \\fr 34:10 \\ft Literally “from wrong” \\f*"},{"style":"q1","text":""},{"style":"v","text":"Indeed, he will repay \\add according to\\add* a human being’s deeds,"},{"style":"q1","text":"and according to a man’s way he will let \\add it\\add* happen \\add to\\add* him."},{"style":"q1","text":""},{"style":"v","text":"What’s more, God truly does not act wickedly,"},{"style":"q1","text":"and Shaddai does not pervert justice."},{"style":"q1","text":""},{"style":"v","text":"Who gave him charge \\add over the\\add* earth?"},{"style":"q1","text":"Or\\f + \\fr 34:13 \\ft Hebrew “And” \\f* who laid on \\add him\\add* \\add the\\add* whole world?"},{"style":"q1","text":""},{"style":"v","text":"If he should set his heart to it,"},{"style":"q1","text":"and he should gather his spirit and his breath to himself,"},{"style":"q1","text":""},{"style":"v","text":"all flesh would perish together,"},{"style":"q1","text":"and humankind would return to dust."},{"style":"q1","text":""},{"style":"v","text":"“But\\f + \\fr 34:16 \\ft Hebrew “And” \\f* if \\add you have\\add* understanding, hear this;"},{"style":"q1","text":"listen to ⸤what I say⸥.\\f + \\fr 34:16 \\ft Literally “the voice/sound of my words” \\f*"},{"style":"q1","text":""},{"style":"v","text":"Shall \\add he who\\add* hates justice really govern?"},{"style":"q1","text":"Or will you\\f + \\fr 34:17 \\ft Singular \\f* declare \\add the\\add* Righteous One, the Mighty, guilty?—"},{"style":"q1","text":""},{"style":"v","text":"the one who says to a king,"},{"style":"q1","text":"‘You worthless man,’ to noblemen, ‘You wicked man,’"},{"style":"q1","text":""},{"style":"v","text":"who ⸤shows no partiality to officials⸥\\f + \\fr 34:19 \\ft Literally “he does not lift the face of officials” \\f*"},{"style":"q1","text":"and \\add who\\add* ⸤does not take note of the noble more than of the insignificant⸥,\\f + \\fr 34:19 \\ft Literally “he does not regard \\fq the \\ft eminent to the face of \\fq the \\ft poor/insignificant” \\f*"},{"style":"q1","text":"for all of them \\add are\\add* the work of his hands?"},{"style":"q1","text":""},{"style":"v","text":"\\add In\\add* a moment they die,"},{"style":"q1","text":"and \\add in\\add* the middle of \\add the\\add* night \\add the\\add* people are shaken, and they pass away,"},{"style":"q1","text":"and they take away \\add the\\add* mighty ⸤effortlessly⸥.\\f + \\fr 34:20 \\ft Literally “not by a hand” \\f*"},{"style":"q1","text":""},{"style":"v","text":"“Indeed, his eyes \\add are\\add* upon \\add the\\add* ways of man,"},{"style":"q1","text":"and he sees all his steps."},{"style":"q1","text":""},{"style":"v","text":"There is no darkness, and there is no deep shadow"},{"style":"q1","text":"where instigators of mischief might hide themselves."},{"style":"q1","text":""},{"style":"v","text":"Indeed, he has not yet appointed \\add a time\\add* for man"},{"style":"q1","text":"to go to God in the judgment."},{"style":"q1","text":""},{"style":"v","text":"He shatters the mighty without investigation,"},{"style":"q1","text":"and he sets others in their place."},{"style":"q1","text":""},{"style":"v","text":"Therefore he knows their works,"},{"style":"q1","text":"and he overturns \\add them\\add* \\add in the\\add* night"},{"style":"q1","text":"⸤so that⸥\\f + \\fr 34:25 \\ft Hebrew “and” \\f* they are crushed."},{"style":"q1","text":""},{"style":"v","text":"He strikes them ⸤where the wicked stood⸥,\\f + \\fr 34:26 \\ft Literally “among \\fq the \\ft wicked” \\f*"},{"style":"q1","text":"⸤where there are onlookers⸥,\\f + \\fr 34:26 \\ft Literally “in \\fq the \\ft place of seers” \\f*"},{"style":"q1","text":""},{"style":"v","text":"because they have turned aside from him"},{"style":"q1","text":"and have not understood any of his ways,"},{"style":"q1","text":""},{"style":"v","text":"so that \\add they\\add* cause \\add the\\add* cry of distress from \\add the\\add* helpless to come to him,"},{"style":"q1","text":"and he hears \\add the\\add* cry of distress from \\add the\\add* needy,"},{"style":"q1","text":""},{"style":"v","text":"but he remains quiet, and who can condemn?"},{"style":"q1","text":"And he hides \\add his\\add* face, and who can behold him?"},{"style":"q1","text":"Yet\\f + \\fr 34:29 \\ft Hebrew “And” \\f* \\add he is\\add* over a nation and over a person alike,"},{"style":"q1","text":""},{"style":"v","text":"so that godless human beings should not reign,"},{"style":"q1","text":"nor those who ensnare \\add the\\add* people."},{"style":"q1","text":""},{"style":"v","text":"“Indeed, does anyone say to God, ‘I have endured \\add chastisement\\add*;"},{"style":"q1","text":"I will not act corruptly \\add again\\add*;"},{"style":"q1","text":""},{"style":"v","text":"teach me yourself ⸤what I cannot see⸥;\\f + \\fr 34:32 \\ft Literally “apart from \\fq what \\ft I can see” \\f*"},{"style":"q1","text":"if I have done wrong, I will not repeat \\add it\\add*’?"},{"style":"q1","text":""},{"style":"v","text":"⸤According to your judgment⸥,\\f + \\fr 34:33 \\ft Literally “from with you” \\f* must he repay \\add it\\add* because you rejected \\add this\\add*?"},{"style":"q1","text":"Indeed, you must choose, and not I, so\\f + \\fr 34:33 \\ft Hebrew “And” \\f* declare what you know."},{"style":"q1","text":""},{"style":"v","text":"⸤Those who have sense⸥\\f + \\fr 34:34 \\ft Literally “Men of heart” \\f* say to me,"},{"style":"q1","text":"and \\add the\\add* wise man hearing me \\add says\\add*:"},{"style":"q1","text":""},{"style":"v","text":"‘Job speaks without knowledge,"},{"style":"q1","text":"and his words \\add are\\add* without insight."},{"style":"q1","text":""},{"style":"v","text":"Would that Job were tested up to \\add the\\add* end"},{"style":"q1","text":"because \\add his\\add* answers \\add are\\add* like \\add those from\\add* men of mischief,"},{"style":"q1","text":""},{"style":"v","text":"for he adds transgression to his sin;"},{"style":"q1","text":"he claps hands among us,"},{"style":"q1","text":"and he multiplies his words against God.’ ”"},{"style":"sd0","text":""}]