[{"style":"p","text":""},{"style":"v","text":"\\w Καὶ|strong=\"G2532\"\\w* \\w εἶδον|strong=\"G3708\"\\w* \\w ἐκ|strong=\"G1537\"\\w* \\w τῆς|strong=\"G3588\"\\w* \\w θαλάσσης|strong=\"G2281\"\\w* \\w θηρίον|strong=\"G2342\"\\w* \\w ἀναβαῖνον|strong=\"G0305\"\\w*, \\w ἔχον|strong=\"G2192\"\\w* \\w κέρατα|strong=\"G2768\"\\w* \\w δέκα|strong=\"G1176\"\\w* \\w καὶ|strong=\"G2532\"\\w* \\w κεφαλὰς|strong=\"G2776\"\\w* \\w ἑπτά|strong=\"G2033\"\\w*, \\w καὶ|strong=\"G2532\"\\w* \\w ἐπὶ|strong=\"G1909\"\\w* \\w τῶν|strong=\"G3588\"\\w* \\w κεράτων|strong=\"G2768\"\\w* \\w αὐτοῦ|strong=\"G0846\"\\w* \\w δέκα|strong=\"G1176\"\\w* \\w διαδήματα|strong=\"G1238\"\\w*, \\w καὶ|strong=\"G2532\"\\w* \\w ἐπὶ|strong=\"G1909\"\\w* \\w τὰς|strong=\"G3588\"\\w* \\w κεφαλὰς|strong=\"G2776\"\\w* \\w αὐτοῦ|strong=\"G0846\"\\w* \\f - \\fr 13:1  \\ft ὀνόματα \\fw WH Treg NA RP\\ft  ] ὄνομα \\+fw NIV\\f*⸀\\w ὀνόματα|strong=\"G3686\"\\w* \\w βλασφημίας|strong=\"G0988\"\\w*. "},{"style":"v","text":"\\w καὶ|strong=\"G2532\"\\w* \\w τὸ|strong=\"G3588\"\\w* \\w θηρίον|strong=\"G2342\"\\w* \\w ὃ|strong=\"G3588\"\\w* \\w εἶδον|strong=\"G3708\"\\w* \\w ἦν|strong=\"G1510\"\\w* \\w ὅμοιον|strong=\"G3664\"\\w* \\w παρδάλει|strong=\"G3917\"\\w*, \\w καὶ|strong=\"G2532\"\\w* \\w οἱ|strong=\"G3588\"\\w* \\w πόδες|strong=\"G4228\"\\w* \\w αὐτοῦ|strong=\"G0846\"\\w* \\w ὡς|strong=\"G5613\"\\w* \\w ἄρκου|strong=\"G0715\"\\w*, \\w καὶ|strong=\"G2532\"\\w* \\w τὸ|strong=\"G3588\"\\w* \\w στόμα|strong=\"G4750\"\\w* \\w αὐτοῦ|strong=\"G0846\"\\w* \\w ὡς|strong=\"G5613\"\\w* \\w στόμα|strong=\"G4750\"\\w* \\w λέοντος|strong=\"G3023\"\\w*. \\w καὶ|strong=\"G2532\"\\w* \\w ἔδωκεν|strong=\"G1325\"\\w* \\w αὐτῷ|strong=\"G0846\"\\w* \\w ὁ|strong=\"G3588\"\\w* \\w δράκων|strong=\"G1404\"\\w* \\w τὴν|strong=\"G3588\"\\w* \\w δύναμιν|strong=\"G1411\"\\w* \\w αὐτοῦ|strong=\"G0846\"\\w* \\w καὶ|strong=\"G2532\"\\w* \\w τὸν|strong=\"G3588\"\\w* \\w θρόνον|strong=\"G2362\"\\w* \\w αὐτοῦ|strong=\"G0846\"\\w* \\w καὶ|strong=\"G2532\"\\w* \\w ἐξουσίαν|strong=\"G1849\"\\w* \\w μεγάλην|strong=\"G3173\"\\w*. "},{"style":"v","text":"\\w καὶ|strong=\"G2532\"\\w* \\w μίαν|strong=\"G1520\"\\w* \\w ἐκ|strong=\"G1537\"\\w* \\w τῶν|strong=\"G3588\"\\w* \\w κεφαλῶν|strong=\"G2776\"\\w* \\w αὐτοῦ|strong=\"G0846\"\\w* \\f - \\fr 13:3  \\ft ὡς \\fw WH Treg NIV\\ft  ] ὡσεὶ \\+fw RP\\f*⸀\\w ὡς|strong=\"G5613\"\\w* \\w ἐσφαγμένην|strong=\"G4969\"\\w* \\w εἰς|strong=\"G1519\"\\w* \\w θάνατον|strong=\"G2288\"\\w*, \\w καὶ|strong=\"G2532\"\\w* \\w ἡ|strong=\"G3588\"\\w* \\w πληγὴ|strong=\"G4127\"\\w* \\w τοῦ|strong=\"G3588\"\\w* \\w θανάτου|strong=\"G2288\"\\w* \\w αὐτοῦ|strong=\"G0846\"\\w* \\w ἐθεραπεύθη|strong=\"G2323\"\\w*. \\w καὶ|strong=\"G2532\"\\w* \\f - \\fr 13:3  \\ft ἐθαυμάσθη \\fw WH Treg NIV\\ft  ] ἐθαύμασεν \\+fw RP\\f*⸀ἐθαυμάσθη \\f - \\fr 13:3  \\ft ὅλη ἡ γῆ \\fw WH NIV RP\\ft  ] ἐν ὅλῃ τῇ γῇ \\+fw Treg\\f*⸂\\w ὅλη|strong=\"G3650\"\\w* \\w ἡ|strong=\"G3588\"\\w* \\w γῆ|strong=\"G1093\"\\w*⸃ \\w ὀπίσω|strong=\"G3694\"\\w* \\w τοῦ|strong=\"G3588\"\\w* \\w θηρίου|strong=\"G2342\"\\w*, "},{"style":"v","text":"\\w καὶ|strong=\"G2532\"\\w* \\w προσεκύνησαν|strong=\"G4352\"\\w* \\w τῷ|strong=\"G3588\"\\w* \\w δράκοντι|strong=\"G1404\"\\w* \\f - \\fr 13:4  \\ft ὅτι ἔδωκεν \\fw WH Treg NIV\\ft  ] τῷ δεδωκότι \\+fw RP\\f*⸂\\w ὅτι|strong=\"G3754\"\\w* \\w ἔδωκεν|strong=\"G1325\"\\w*⸃ \\w τὴν|strong=\"G3588\"\\w* \\w ἐξουσίαν|strong=\"G1849\"\\w* \\w τῷ|strong=\"G3588\"\\w* \\w θηρίῳ|strong=\"G2342\"\\w*, \\w καὶ|strong=\"G2532\"\\w* \\w προσεκύνησαν|strong=\"G4352\"\\w* \\w τῷ|strong=\"G3588\"\\w* \\w θηρίῳ|strong=\"G2342\"\\w* \\w λέγοντες|strong=\"G3004\"\\w*· \\w Τίς|strong=\"G5100\"\\w* \\w ὅμοιος|strong=\"G3664\"\\w* \\w τῷ|strong=\"G3588\"\\w* \\w θηρίῳ|strong=\"G2342\"\\w*, \\w καὶ|strong=\"G2532\"\\w* \\w τίς|strong=\"G5100\"\\w* \\f - \\fr 13:4  \\ft δύναται \\fw WH Treg NIV\\ft  ] δύνατος \\+fw RP\\f*⸀\\w δύναται|strong=\"G1410\"\\w* \\w πολεμῆσαι|strong=\"G4170\"\\w* \\w μετ|strong=\"G3326\"\\w*᾽ \\w αὐτοῦ|strong=\"G0846\"\\w*; "},{"style":"p","text":""},{"style":"v","text":"\\w Καὶ|strong=\"G2532\"\\w* \\w ἐδόθη|strong=\"G1325\"\\w* \\w αὐτῷ|strong=\"G0846\"\\w* \\w στόμα|strong=\"G4750\"\\w* \\w λαλοῦν|strong=\"G2980\"\\w* \\w μεγάλα|strong=\"G3173\"\\w* \\w καὶ|strong=\"G2532\"\\w* \\f - \\fr 13:5  \\ft βλασφημίας \\fw WH Treg NIV\\ft  ] βλασφημίαν \\+fw RP\\f*⸀\\w βλασφημίας|strong=\"G0988\"\\w*, \\w καὶ|strong=\"G2532\"\\w* \\w ἐδόθη|strong=\"G1325\"\\w* \\w αὐτῷ|strong=\"G0846\"\\w* \\f - \\fr 13:5  \\ft ἐξουσία \\fw WH Treg NIV\\ft  ] + πόλεμον \\+fw RP\\f*⸀\\w ἐξουσία|strong=\"G1849\"\\w* \\w ποιῆσαι|strong=\"G4160\"\\w* \\w μῆνας|strong=\"G3376\"\\w* \\f - \\fr 13:5  \\ft τεσσεράκοντα \\fw Treg\\ft  ] + καὶ \\+fw WH NIV\\ft ; τεσσαράκοντα \\+fw RP\\f*⸀τεσσεράκοντα \\w δύο|strong=\"G1417\"\\w*. "},{"style":"v","text":"\\w καὶ|strong=\"G2532\"\\w* ἤνοιξε \\w τὸ|strong=\"G3588\"\\w* \\w στόμα|strong=\"G4750\"\\w* \\w αὐτοῦ|strong=\"G0846\"\\w* \\w εἰς|strong=\"G1519\"\\w* \\f - \\fr 13:6  \\ft βλασφημίας \\fw WH Treg NIV\\ft  ] βλασφημίαν \\+fw RP\\f*⸀\\w βλασφημίας|strong=\"G0988\"\\w* \\w πρὸς|strong=\"G4314\"\\w* \\w τὸν|strong=\"G3588\"\\w* \\w θεόν|strong=\"G2316\"\\w*, \\w βλασφημῆσαι|strong=\"G0987\"\\w* \\w τὸ|strong=\"G3588\"\\w* \\w ὄνομα|strong=\"G3686\"\\w* \\w αὐτοῦ|strong=\"G0846\"\\w* \\w καὶ|strong=\"G2532\"\\w* \\w τὴν|strong=\"G3588\"\\w* \\w σκηνὴν|strong=\"G4633\"\\w* \\w αὐτοῦ|strong=\"G0846\"\\w*, \\w τοὺς|strong=\"G3588\"\\w* \\w ἐν|strong=\"G1722\"\\w* \\w τῷ|strong=\"G3588\"\\w* \\w οὐρανῷ|strong=\"G3772\"\\w* \\w σκηνοῦντας|strong=\"G4637\"\\w*. "},{"style":"v","text":"\\w καὶ|strong=\"G2532\"\\w* \\w ἐδόθη|strong=\"G1325\"\\w* \\w αὐτῷ|strong=\"G0846\"\\w* \\w ποιῆσαι|strong=\"G4160\"\\w* \\w πόλεμον|strong=\"G4171\"\\w* \\w μετὰ|strong=\"G3326\"\\w* \\w τῶν|strong=\"G3588\"\\w* \\w ἁγίων|strong=\"G0040\"\\w* \\w καὶ|strong=\"G2532\"\\w* \\w νικῆσαι|strong=\"G3528\"\\w* \\w αὐτούς|strong=\"G0846\"\\w*, \\w καὶ|strong=\"G2532\"\\w* \\w ἐδόθη|strong=\"G1325\"\\w* \\w αὐτῷ|strong=\"G0846\"\\w* \\w ἐξουσία|strong=\"G1849\"\\w* \\w ἐπὶ|strong=\"G1909\"\\w* \\w πᾶσαν|strong=\"G3956\"\\w* \\w φυλὴν|strong=\"G5443\"\\w* \\w καὶ|strong=\"G2532\"\\w* \\w λαὸν|strong=\"G2992\"\\w* \\w καὶ|strong=\"G2532\"\\w* \\w γλῶσσαν|strong=\"G1100\"\\w* \\w καὶ|strong=\"G2532\"\\w* \\w ἔθνος|strong=\"G1484\"\\w*. "},{"style":"v","text":"\\w καὶ|strong=\"G2532\"\\w* \\w προσκυνήσουσιν|strong=\"G4352\"\\w* \\f - \\fr 13:8  \\ft αὐτὸν \\fw WH Treg NIV\\ft  ] αὐτῷ \\+fw RP\\f*⸀\\w αὐτὸν|strong=\"G0846\"\\w* \\w πάντες|strong=\"G3956\"\\w* \\w οἱ|strong=\"G3588\"\\w* \\w κατοικοῦντες|strong=\"G2730\"\\w* \\w ἐπὶ|strong=\"G1909\"\\w* \\w τῆς|strong=\"G3588\"\\w* \\w γῆς|strong=\"G1093\"\\w*, \\f - \\fr 13:8  \\ft οὗ \\fw WH Treg NIV\\ft  ] ὧν \\+fw RP\\f*⸀\\w οὗ|strong=\"G3756\"\\w* \\w οὐ|strong=\"G3756\"\\w* \\w γέγραπται|strong=\"G1125\"\\w* \\w τὸ|strong=\"G3588\"\\w* \\w ὄνομα|strong=\"G3686\"\\w* \\f - \\fr 13:8  \\ft αὐτοῦ \\fw WH Treg NIV\\ft  ] – \\+fw RP\\f*⸀\\w αὐτοῦ|strong=\"G0846\"\\w* \\w ἐν|strong=\"G1722\"\\w* \\w τῷ|strong=\"G3588\"\\w* \\w βιβλίῳ|strong=\"G0975\"\\w* \\w τῆς|strong=\"G3588\"\\w* \\w ζωῆς|strong=\"G2222\"\\w* \\w τοῦ|strong=\"G3588\"\\w* \\w ἀρνίου|strong=\"G0721\"\\w* \\w τοῦ|strong=\"G3588\"\\w* \\w ἐσφαγμένου|strong=\"G4969\"\\w* \\w ἀπὸ|strong=\"G0575\"\\w* \\w καταβολῆς|strong=\"G2602\"\\w* \\w κόσμου|strong=\"G2889\"\\w*. "},{"style":"p","text":""},{"style":"v","text":"\\w Εἴ|strong=\"G1487\"\\w* \\w τις|strong=\"G5100\"\\w* \\w ἔχει|strong=\"G2192\"\\w* \\w οὖς|strong=\"G3739\"\\w* \\w ἀκουσάτω|strong=\"G0191\"\\w*. "},{"style":"v","text":"\\w εἴ|strong=\"G1487\"\\w* \\w τις|strong=\"G5100\"\\w* \\f - \\fr 13:10  \\ft εἰς αἰχμαλωσίαν, εἰς αἰχμαλωσίαν \\fw WH NIV\\ft  ] εἰς αἰχμαλωσίαν \\+fw Treg\\ft ; ἔχει αἰχμαλωσίαν \\+fw RP\\f*⸂\\w εἰς|strong=\"G1519\"\\w* \\w αἰχμαλωσίαν|strong=\"G0161\"\\w*, \\w εἰς|strong=\"G1519\"\\w* \\w αἰχμαλωσίαν|strong=\"G0161\"\\w*⸃ \\w ὑπάγει|strong=\"G5217\"\\w*· \\w εἴ|strong=\"G1487\"\\w* \\w τις|strong=\"G5100\"\\w* \\w ἐν|strong=\"G1722\"\\w* μαχαίρῃ \\f - \\fr 13:10  \\ft ἀποκτανθῆναι \\fw NIV\\ft  ] ἀποκτενεῖ δεῖ \\+fw WH Treg RP\\f*⸀\\w ἀποκτανθῆναι|strong=\"G0615\"\\w* \\w αὐτὸν|strong=\"G0846\"\\w* \\w ἐν|strong=\"G1722\"\\w* μαχαίρῃ \\w ἀποκτανθῆναι|strong=\"G0615\"\\w*. \\w ὧδέ|strong=\"G5602\"\\w* \\w ἐστιν|strong=\"G1510\"\\w* \\w ἡ|strong=\"G3588\"\\w* \\w ὑπομονὴ|strong=\"G5281\"\\w* \\w καὶ|strong=\"G2532\"\\w* \\w ἡ|strong=\"G3588\"\\w* \\w πίστις|strong=\"G4102\"\\w* \\w τῶν|strong=\"G3588\"\\w* \\w ἁγίων|strong=\"G0040\"\\w*. "},{"style":"p","text":""},{"style":"v","text":"\\w Καὶ|strong=\"G2532\"\\w* \\w εἶδον|strong=\"G3708\"\\w* \\w ἄλλο|strong=\"G0243\"\\w* \\w θηρίον|strong=\"G2342\"\\w* \\w ἀναβαῖνον|strong=\"G0305\"\\w* \\w ἐκ|strong=\"G1537\"\\w* \\w τῆς|strong=\"G3588\"\\w* \\w γῆς|strong=\"G1093\"\\w*, \\w καὶ|strong=\"G2532\"\\w* \\w εἶχεν|strong=\"G2192\"\\w* \\w κέρατα|strong=\"G2768\"\\w* \\w δύο|strong=\"G1417\"\\w* \\w ὅμοια|strong=\"G3664\"\\w* \\w ἀρνίῳ|strong=\"G0721\"\\w*, \\w καὶ|strong=\"G2532\"\\w* \\w ἐλάλει|strong=\"G2980\"\\w* \\w ὡς|strong=\"G5613\"\\w* \\w δράκων|strong=\"G1404\"\\w*. "},{"style":"v","text":"\\w καὶ|strong=\"G2532\"\\w* \\w τὴν|strong=\"G3588\"\\w* \\w ἐξουσίαν|strong=\"G1849\"\\w* \\w τοῦ|strong=\"G3588\"\\w* \\w πρώτου|strong=\"G4413\"\\w* \\w θηρίου|strong=\"G2342\"\\w* \\w πᾶσαν|strong=\"G3956\"\\w* \\w ποιεῖ|strong=\"G4160\"\\w* \\w ἐνώπιον|strong=\"G1799\"\\w* \\w αὐτοῦ|strong=\"G0846\"\\w*. \\w καὶ|strong=\"G2532\"\\w* \\f - \\fr 13:12  \\ft ποιεῖ \\fw WH Treg NIV\\ft  ] ἐποίει \\+fw RP\\f*⸀\\w ποιεῖ|strong=\"G4160\"\\w* \\w τὴν|strong=\"G3588\"\\w* \\w γῆν|strong=\"G1093\"\\w* \\w καὶ|strong=\"G2532\"\\w* \\w τοὺς|strong=\"G3588\"\\w* \\w ἐν|strong=\"G1722\"\\w* \\w αὐτῇ|strong=\"G0846\"\\w* \\w κατοικοῦντας|strong=\"G2730\"\\w* \\w ἵνα|strong=\"G2443\"\\w* \\f - \\fr 13:12  \\ft προσκυνήσουσιν \\fw WH Treg NIV\\ft  ] προσκυνήσωσιν \\+fw RP\\f*⸀\\w προσκυνήσουσιν|strong=\"G4352\"\\w* \\w τὸ|strong=\"G3588\"\\w* \\w θηρίον|strong=\"G2342\"\\w* \\w τὸ|strong=\"G3588\"\\w* \\w πρῶτον|strong=\"G4412\"\\w*, \\w οὗ|strong=\"G3756\"\\w* \\w ἐθεραπεύθη|strong=\"G2323\"\\w* \\w ἡ|strong=\"G3588\"\\w* \\w πληγὴ|strong=\"G4127\"\\w* \\w τοῦ|strong=\"G3588\"\\w* \\w θανάτου|strong=\"G2288\"\\w* \\w αὐτοῦ|strong=\"G0846\"\\w*. "},{"style":"v","text":"\\w καὶ|strong=\"G2532\"\\w* \\w ποιεῖ|strong=\"G4160\"\\w* \\w σημεῖα|strong=\"G4592\"\\w* \\w μεγάλα|strong=\"G3173\"\\w*, \\f - \\fr 13:13  \\ft ἵνα καὶ πῦρ ποιῇ \\fw WH Treg NIV\\ft  ] καὶ πῦρ ἵνα \\+fw RP\\f*⸂\\w ἵνα|strong=\"G2443\"\\w* \\w καὶ|strong=\"G2532\"\\w* \\w πῦρ|strong=\"G4442\"\\w* \\w ποιῇ|strong=\"G4160\"\\w*⸃ \\w ἐκ|strong=\"G1537\"\\w* \\w τοῦ|strong=\"G3588\"\\w* \\w οὐρανοῦ|strong=\"G3772\"\\w* \\f - \\fr 13:13  \\ft καταβαίνειν εἰς \\fw WH Treg NIV\\ft  ] καταβαίνῃ ἐπὶ \\+fw RP\\f*⸂\\w καταβαίνειν|strong=\"G2597\"\\w* \\w εἰς|strong=\"G1519\"\\w*⸃ \\w τὴν|strong=\"G3588\"\\w* \\w γῆν|strong=\"G1093\"\\w* \\w ἐνώπιον|strong=\"G1799\"\\w* \\w τῶν|strong=\"G3588\"\\w* \\w ἀνθρώπων|strong=\"G0444\"\\w*. "},{"style":"v","text":"\\w καὶ|strong=\"G2532\"\\w* \\w πλανᾷ|strong=\"G4105\"\\w* \\f - \\fr 13:14  \\ft τοὺς \\fw WH Treg NIV\\ft  ] + ἐμοὺς τοὺς \\+fw RP\\f*⸀\\w τοὺς|strong=\"G3588\"\\w* \\w κατοικοῦντας|strong=\"G2730\"\\w* \\w ἐπὶ|strong=\"G1909\"\\w* \\w τῆς|strong=\"G3588\"\\w* \\w γῆς|strong=\"G1093\"\\w* \\w διὰ|strong=\"G1223\"\\w* \\w τὰ|strong=\"G3588\"\\w* \\w σημεῖα|strong=\"G4592\"\\w* \\w ἃ|strong=\"G3739\"\\w* \\w ἐδόθη|strong=\"G1325\"\\w* \\w αὐτῷ|strong=\"G0846\"\\w* \\w ποιῆσαι|strong=\"G4160\"\\w* \\w ἐνώπιον|strong=\"G1799\"\\w* \\w τοῦ|strong=\"G3588\"\\w* \\w θηρίου|strong=\"G2342\"\\w*, \\w λέγων|strong=\"G3004\"\\w* \\w τοῖς|strong=\"G3588\"\\w* \\w κατοικοῦσιν|strong=\"G2730\"\\w* \\w ἐπὶ|strong=\"G1909\"\\w* \\w τῆς|strong=\"G3588\"\\w* \\w γῆς|strong=\"G1093\"\\w* \\w ποιῆσαι|strong=\"G4160\"\\w* \\w εἰκόνα|strong=\"G1504\"\\w* \\w τῷ|strong=\"G3588\"\\w* \\w θηρίῳ|strong=\"G2342\"\\w*, \\f - \\fr 13:14  \\ft ὃς ἔχει \\fw WH Treg NIV\\ft  ] ὃ εἶχεν \\+fw RP\\f*⸂\\w ὃς|strong=\"G3739\"\\w* \\w ἔχει|strong=\"G2192\"\\w*⸃ \\w τὴν|strong=\"G3588\"\\w* \\w πληγὴν|strong=\"G4127\"\\w* \\f - \\fr 13:14  \\ft τῆς μαχαίρης καὶ ἔζησεν \\fw WH Treg NIV\\ft  ] καὶ ἔζησεν ἀπὸ τῆς μαχαίρας \\+fw RP\\f*⸂\\w τῆς|strong=\"G3588\"\\w* μαχαίρης \\w καὶ|strong=\"G2532\"\\w* \\w ἔζησεν|strong=\"G2198\"\\w*⸃. "},{"style":"v","text":"\\w καὶ|strong=\"G2532\"\\w* \\w ἐδόθη|strong=\"G1325\"\\w* \\f - \\fr 13:15  \\ft αὐτῷ \\fw Treg NIV RP\\ft  ] αὐτῇ \\+fw WH\\f*⸀\\w αὐτῷ|strong=\"G0846\"\\w* \\f - \\fr 13:15  \\ft δοῦναι πνεῦμα \\fw WH Treg NIV\\ft  ] πνεῦμα δοῦναι \\+fw RP\\f*⸂\\w δοῦναι|strong=\"G1325\"\\w* \\w πνεῦμα|strong=\"G4151\"\\w*⸃ \\w τῇ|strong=\"G3588\"\\w* \\w εἰκόνι|strong=\"G1504\"\\w* \\w τοῦ|strong=\"G3588\"\\w* \\w θηρίου|strong=\"G2342\"\\w*, \\w ἵνα|strong=\"G2443\"\\w* \\w καὶ|strong=\"G2532\"\\w* \\w λαλήσῃ|strong=\"G2980\"\\w* \\w ἡ|strong=\"G3588\"\\w* \\w εἰκὼν|strong=\"G1504\"\\w* \\w τοῦ|strong=\"G3588\"\\w* \\w θηρίου|strong=\"G2342\"\\w* \\w καὶ|strong=\"G2532\"\\w* \\w ποιήσῃ|strong=\"G4160\"\\w* \\f - \\fr 13:15  \\ft ἵνα \\fw WH Treg NIV\\ft  ] – \\+fw RP\\f*⸀\\w ἵνα|strong=\"G2443\"\\w* \\w ὅσοι|strong=\"G3745\"\\w* \\w ἐὰν|strong=\"G1437\"\\w* \\w μὴ|strong=\"G3361\"\\w* \\w προσκυνήσωσιν|strong=\"G4352\"\\w* \\w τῇ|strong=\"G3588\"\\w* \\w εἰκόνι|strong=\"G1504\"\\w* \\w τοῦ|strong=\"G3588\"\\w* \\w θηρίου|strong=\"G2342\"\\w* \\w ἀποκτανθῶσιν|strong=\"G0615\"\\w*. "},{"style":"v","text":"\\w καὶ|strong=\"G2532\"\\w* \\w ποιεῖ|strong=\"G4160\"\\w* \\w πάντας|strong=\"G3956\"\\w*, \\w τοὺς|strong=\"G3588\"\\w* \\w μικροὺς|strong=\"G3398\"\\w* \\w καὶ|strong=\"G2532\"\\w* \\w τοὺς|strong=\"G3588\"\\w* \\w μεγάλους|strong=\"G3173\"\\w*, \\w καὶ|strong=\"G2532\"\\w* \\w τοὺς|strong=\"G3588\"\\w* \\w πλουσίους|strong=\"G4145\"\\w* \\w καὶ|strong=\"G2532\"\\w* \\w τοὺς|strong=\"G3588\"\\w* \\w πτωχούς|strong=\"G4434\"\\w*, \\w καὶ|strong=\"G2532\"\\w* \\w τοὺς|strong=\"G3588\"\\w* \\w ἐλευθέρους|strong=\"G1658\"\\w* \\w καὶ|strong=\"G2532\"\\w* \\w τοὺς|strong=\"G3588\"\\w* \\w δούλους|strong=\"G1401\"\\w*, \\w ἵνα|strong=\"G2443\"\\w* \\f - \\fr 13:16  \\ft δῶσιν \\fw WH Treg NIV\\ft  ] δώσωσιν \\+fw RP\\f*⸀\\w δῶσιν|strong=\"G1325\"\\w* \\w αὐτοῖς|strong=\"G0846\"\\w* \\f - \\fr 13:16  \\ft χάραγμα \\fw WH Treg NIV\\ft  ] χαράγματα \\+fw RP\\f*⸀\\w χάραγμα|strong=\"G5480\"\\w* \\w ἐπὶ|strong=\"G1909\"\\w* \\w τῆς|strong=\"G3588\"\\w* \\w χειρὸς|strong=\"G5495\"\\w* \\w αὐτῶν|strong=\"G0846\"\\w* \\w τῆς|strong=\"G3588\"\\w* \\w δεξιᾶς|strong=\"G1188\"\\w* \\w ἢ|strong=\"G3588\"\\w* \\w ἐπὶ|strong=\"G1909\"\\w* \\w τὸ|strong=\"G3588\"\\w* \\w μέτωπον|strong=\"G3359\"\\w* \\w αὐτῶν|strong=\"G0846\"\\w*, "},{"style":"v","text":"\\w καὶ|strong=\"G2532\"\\w* \\w ἵνα|strong=\"G2443\"\\w* \\w μή|strong=\"G3361\"\\w* \\w τις|strong=\"G5100\"\\w* \\f - \\fr 13:17  \\ft δύνηται \\fw WH Treg NIV\\ft  ] δύναται \\+fw RP\\f*⸀\\w δύνηται|strong=\"G1410\"\\w* \\w ἀγοράσαι|strong=\"G0059\"\\w* \\w ἢ|strong=\"G3588\"\\w* \\w πωλῆσαι|strong=\"G4453\"\\w* \\w εἰ|strong=\"G1487\"\\w* \\w μὴ|strong=\"G3361\"\\w* \\w ὁ|strong=\"G3588\"\\w* \\w ἔχων|strong=\"G2192\"\\w* \\w τὸ|strong=\"G3588\"\\w* \\w χάραγμα|strong=\"G5480\"\\w*, \\w τὸ|strong=\"G3588\"\\w* \\w ὄνομα|strong=\"G3686\"\\w* \\w τοῦ|strong=\"G3588\"\\w* \\w θηρίου|strong=\"G2342\"\\w* \\w ἢ|strong=\"G3588\"\\w* \\w τὸν|strong=\"G3588\"\\w* \\w ἀριθμὸν|strong=\"G0706\"\\w* \\w τοῦ|strong=\"G3588\"\\w* \\w ὀνόματος|strong=\"G3686\"\\w* \\w αὐτοῦ|strong=\"G0846\"\\w*. "},{"style":"v","text":"\\w ὧδε|strong=\"G5602\"\\w* \\w ἡ|strong=\"G3588\"\\w* \\w σοφία|strong=\"G4678\"\\w* \\w ἐστίν|strong=\"G1510\"\\w*· \\w ὁ|strong=\"G3588\"\\w* \\w ἔχων|strong=\"G2192\"\\w* \\w νοῦν|strong=\"G3563\"\\w* \\w ψηφισάτω|strong=\"G5585\"\\w* \\w τὸν|strong=\"G3588\"\\w* \\w ἀριθμὸν|strong=\"G0706\"\\w* \\w τοῦ|strong=\"G3588\"\\w* \\w θηρίου|strong=\"G2342\"\\w*, \\w ἀριθμὸς|strong=\"G0706\"\\w* \\w γὰρ|strong=\"G1063\"\\w* \\w ἀνθρώπου|strong=\"G0444\"\\w* \\w ἐστίν|strong=\"G1510\"\\w*· \\w καὶ|strong=\"G2532\"\\w* \\w ὁ|strong=\"G3588\"\\w* \\w ἀριθμὸς|strong=\"G0706\"\\w* \\f - \\fr 13:18  \\ft αὐτοῦ \\fw WH NIV\\ft  ] + ἐστὶν \\+fw Treg RP\\f*⸀\\w αὐτοῦ|strong=\"G0846\"\\w* \\f - \\fr 13:18  \\ft ἑξακόσιοι ἑξήκοντα ἕξ \\fw WH NIV\\ft  ] ἑξακόσια ἑξήκοντα ἕξ \\+fw RP\\ft ; χξϛ΄ \\+fw Treg\\f*⸂ἑξακόσιοι \\w ἑξήκοντα|strong=\"G1835\"\\w* \\w ἕξ|strong=\"G1537\"\\w*⸃. "}]