[{"style":"s1","text":"Màggalleen Ki sàkk lépp"},{"style":"q1","text":""},{"style":"v","text":"Naa sant Aji Sax ji ci saa xol bii!"},{"style":"q1","text":"Aji Sax ji sama Yàlla, yaaka màgga màgg."},{"style":"q1","text":"Teddngaak\\f + \\fr 104.1 \\fk Teddnga \\ft mooy teraanga ju bare lool.\\f* daraja nga soloo,"},{"style":"q1","text":""},{"style":"v","text":"làmboo leer ni mbubb,"},{"style":"q1","text":"firi asamaan ni ndimo,"},{"style":"q1","text":""},{"style":"v","text":"xadd say néegi kaw ci biir ndox mi,"},{"style":"q1","text":"def niir yi say waruwaay,"},{"style":"q1","text":"di daagoo kaw laafi ngelaw,"},{"style":"q1","text":""},{"style":"v","text":"def ngelaw yi say ndaw,"},{"style":"q1","text":"ay sawara boy, di say jawriñ."},{"style":"q1","text":""},{"style":"v","text":"Yaa dëj suuf ci fondmaam,"},{"style":"q1","text":"deesu ko yëngal ba fàww."},{"style":"q1","text":""},{"style":"v","text":"Yaa ko sànge xóotey géej ni mbubb,"},{"style":"q1","text":"ndox ma taxaw, tiim tund ya."},{"style":"q1","text":""},{"style":"v","text":"Nga gëdd, ndox ma fëx;"},{"style":"q1","text":"nga dënu, mu daw,"},{"style":"q1","text":""},{"style":"v","text":"wale kaw tund ya, wàccsi xur ya,"},{"style":"q1","text":"di béreb ba nga ko beral."},{"style":"q1","text":""},{"style":"v","text":"Ag kemu nga teg, du ko wees,"},{"style":"q1","text":"te dootul muur suuf si."},{"style":"q1","text":""},{"style":"v","text":"Yaa ballal bëti ndox ya ca xur ya,"},{"style":"q1","text":"ñuy wale digg tund ya,"},{"style":"q1","text":""},{"style":"v","text":"ngay nàndal bépp ndundatu àll,"},{"style":"q1","text":"di wëgg mbaamu àll,"},{"style":"q1","text":""},{"style":"v","text":"njanaaw dëkke ca wet ga,"},{"style":"q1","text":"baatam jibe fa garab ya."},{"style":"q1","text":""},{"style":"v","text":"Yaa suuxate tund ya fa sa néegi kaw,"},{"style":"q1","text":"sa liggéey reggal suuf."},{"style":"b","text":""},{"style":"q1","text":""},{"style":"v","text":"Yaa saxalal jur gi ñax"},{"style":"q1","text":"ak gàncax gu doom aadama di bey,"},{"style":"q1","text":"ba génnee ab dund fi suuf,"},{"style":"q1","text":""},{"style":"v","text":"dugub di ko dooleel,"},{"style":"q1","text":"biiñ di bégal xolam,"},{"style":"q1","text":"ag diw di leeral kanamam."},{"style":"q1","text":""},{"style":"v","text":"Garabi Aji Sax ja, seedari Libaŋ"},{"style":"q2","text":"ya mu jëmbat, regg nañu,"},{"style":"q1","text":""},{"style":"v","text":"picc tàgge ca,"},{"style":"q1","text":"xodd dëkke garab gu dul ruus,"},{"style":"q1","text":""},{"style":"v","text":"tund wu mag ñeel kéwéli àll,"},{"style":"q1","text":"doj yi di rawtub daman\\f + \\fr 104.18 \\fk daman \\ft xaw naa nirook njomboor.\\f*."},{"style":"q1","text":""},{"style":"v","text":"Yaa sàkk weer, muy takku jamono,"},{"style":"q1","text":"sàkk jant, mu xam waxtuw fatoom."},{"style":"q1","text":""},{"style":"v","text":"Yaa def lëndëm, mu guddi;"},{"style":"q1","text":"bépp rabu àll di ca dox,"},{"style":"q1","text":""},{"style":"v","text":"gaynde gu mat ŋaral am pàddam,"},{"style":"q1","text":"di sàkkoo dundam fa Yàlla."},{"style":"q1","text":""},{"style":"v","text":"Bu jant fenkee, ñu dellu,"},{"style":"q1","text":"goori ca seeni pax,"},{"style":"q1","text":""},{"style":"v","text":"doom aadama tàmbali kër-këram,"},{"style":"q1","text":"di yendoo liggéey ba ngoon."},{"style":"b","text":""},{"style":"q1","text":""},{"style":"v","text":"Éy Aji Sax ji, yaa bare loo liggéey,"},{"style":"q1","text":"te lépp di xel mu rafet."},{"style":"q1","text":"Suuf daa fees ak say càkkéef."},{"style":"q1","text":""},{"style":"v","text":"Géej a ngee réy te yaa,"},{"style":"q1","text":"la fay yëngu maneesu koo lim,"},{"style":"q1","text":"muy ndundat lu mag ak lu ndaw."},{"style":"q1","text":""},{"style":"v","text":"Fa la gaal di daw,"},{"style":"q1","text":"ak ngaaka la nga bind, mu di fa fowe."},{"style":"q1","text":""},{"style":"v","text":"Ñoom ñépp yaw lañuy séentu,"},{"style":"q1","text":"ngir bu jotee, nga leel leen,"},{"style":"q1","text":""},{"style":"v","text":"may leen lu ñu for;"},{"style":"q1","text":"ŋëbal leen, ñu suur ngëneel."},{"style":"q1","text":""},{"style":"v","text":"Soo leen làqoo, ñu tiit;"},{"style":"q1","text":"nga rocci seen noo, ñu saay,"},{"style":"q1","text":"dellu di pënd."},{"style":"q1","text":""},{"style":"v","text":"Yaay yónnee sag noo, ñu nekk;"},{"style":"q1","text":"te yaay yeesal li ci kaw suuf."},{"style":"b","text":""},{"style":"q1","text":""},{"style":"v","text":"Yal na darajay Aji Sax ji sax,"},{"style":"q1","text":"yal na Aji Sax ji bégey jalooreem."},{"style":"q1","text":""},{"style":"v","text":"Kee naan jàkk suuf, muy lox;"},{"style":"q1","text":"mu laal tund yi, ñuy saxaar!"},{"style":"q1","text":""},{"style":"v","text":"Naa woy Aji Sax ji li feek may dund,"},{"style":"q1","text":"naa kañ sama Yàlla li feek may tooy."},{"style":"q1","text":""},{"style":"v","text":"Sama xalaat bii, yal na ko neex."},{"style":"q1","text":"Man de maa ngi bége Aji Sax ji!"},{"style":"q1","text":""},{"style":"v","text":"Yal na bàkkaarkat raaf fi kaw suuf,"},{"style":"q1","text":"te ku bon noppee nekk."},{"style":"q1","text":"Naa sant Aji Sax ji ci saa xol bii."},{"style":"q1","text":"Màggalleen Ki Sax!"}]