[{"style":"s1","verse":"","text":"Cantique de David, délivré de ses ennemis"},{"style":"r","verse":"","text":"V. 1-51: cf. (Ps 18; 144:1-10.) Ex 15:1, etc. Jg 5:1, etc."},{"style":"p","verse":"","text":""},{"style":"v","verse":"1","text":"David adressa à l’Éternel les paroles de ce cantique, lorsque l’Éternel l’eut délivré de la main de tous ses ennemis et de la main de Saül. "},{"style":"v","verse":"2","text":"Il dit:"},{"style":"q1","verse":"","text":"\\x a \\xo 22.2 \\xt Ps 18:22, etc.\\x*L’Éternel est mon rocher, ma forteresse, mon libérateur."},{"style":"q1","verse":"","text":""},{"style":"v","verse":"3","text":"Dieu est mon rocher, \\x b \\xo 22.3 \\xt Hé 2:13.\\x*où je trouve un abri,"},{"style":"q1","verse":"","text":"Mon bouclier et la force qui me sauve,"},{"style":"q1","verse":"","text":"Ma haute retraite et mon refuge."},{"style":"q1","verse":"","text":"O mon Sauveur! Tu me garantis de la violence."},{"style":"q1","verse":"","text":""},{"style":"v","verse":"4","text":"Je m’écrie: Loué soit l’Éternel!"},{"style":"q1","verse":"","text":"Et je suis délivré de mes ennemis."},{"style":"q1","verse":"","text":""},{"style":"v","verse":"5","text":"Car les flots de la mort m’avaient environné,"},{"style":"q1","verse":"","text":"Les torrents de la destruction m’avaient épouvanté;"},{"style":"q1","verse":"","text":""},{"style":"v","verse":"6","text":"Les liens du sépulcre m’avaient entouré,"},{"style":"q1","verse":"","text":"Les filets de la mort m’avaient surpris."},{"style":"q1","verse":"","text":""},{"style":"v","verse":"7","text":"Dans ma détresse, j’ai invoqué l’Éternel,"},{"style":"q1","verse":"","text":"J’ai invoqué mon Dieu;"},{"style":"q1","verse":"","text":"De son palais, il a entendu ma voix,"},{"style":"q1","verse":"","text":"Et mon cri est parvenu à ses oreilles."},{"style":"q1","verse":"","text":""},{"style":"v","verse":"8","text":"La terre fut ébranlée et trembla,"},{"style":"q1","verse":"","text":"Les fondements des cieux frémirent,"},{"style":"q1","verse":"","text":"Et ils furent ébranlés, parce qu’il était irrité."},{"style":"q1","verse":"","text":""},{"style":"v","verse":"9","text":"Il s’élevait de la fumée dans ses narines,"},{"style":"q1","verse":"","text":"Et un feu dévorant sortait de sa bouche:"},{"style":"q1","verse":"","text":"Il en jaillissait des charbons embrasés."},{"style":"q1","verse":"","text":""},{"style":"v","verse":"10","text":"Il abaissa les cieux, et il descendit:"},{"style":"q1","verse":"","text":"Il y avait une épaisse nuée sous ses pieds."},{"style":"q1","verse":"","text":""},{"style":"v","verse":"11","text":"Il était monté sur un chérubin,"},{"style":"q1","verse":"","text":"et il volait,"},{"style":"q1","verse":"","text":"Il paraissait sur les ailes du vent."},{"style":"q1","verse":"","text":""},{"style":"v","verse":"12","text":"Il faisait des ténèbres une tente autour de lui,"},{"style":"q1","verse":"","text":"Il était enveloppé d’amas d’eaux et de sombres nuages."},{"style":"q1","verse":"","text":""},{"style":"v","verse":"13","text":"De la splendeur qui le précédait"},{"style":"q1","verse":"","text":"S’élançaient des charbons de feu."},{"style":"q1","verse":"","text":""},{"style":"v","verse":"14","text":"L’Éternel tonna des cieux,"},{"style":"q1","verse":"","text":"Le Très-Haut fit retentir sa voix;"},{"style":"q1","verse":"","text":""},{"style":"v","verse":"15","text":"Il lança des flèches et dispersa mes ennemis,"},{"style":"q1","verse":"","text":"La foudre, et les mit en déroute."},{"style":"q1","verse":"","text":""},{"style":"v","verse":"16","text":"Le lit de la mer apparut,"},{"style":"q1","verse":"","text":"Les fondements du monde furent découverts,"},{"style":"q1","verse":"","text":"Par la menace de l’Éternel,"},{"style":"q1","verse":"","text":"Par le bruit du souffle de ses narines."},{"style":"q1","verse":"","text":""},{"style":"v","verse":"17","text":"Il étendit sa main d’en haut, il me saisit,"},{"style":"q1","verse":"","text":"Il me retira des grandes eaux;"},{"style":"q1","verse":"","text":""},{"style":"v","verse":"18","text":"Il me délivra de mon adversaire puissant,"},{"style":"q1","verse":"","text":"De mes ennemis qui étaient plus forts que moi."},{"style":"q1","verse":"","text":""},{"style":"v","verse":"19","text":"Ils m’avaient surpris au jour de ma détresse,"},{"style":"q1","verse":"","text":"Mais l’Éternel fut mon appui."},{"style":"q1","verse":"","text":""},{"style":"v","verse":"20","text":"Il m’a mis au large,"},{"style":"q1","verse":"","text":"Il m’a sauvé, parce qu’il m’aime."},{"style":"q1","verse":"","text":""},{"style":"v","verse":"21","text":"L’Éternel m’a traité selon ma droiture,"},{"style":"q1","verse":"","text":"Il m’a rendu selon la pureté de mes mains;"},{"style":"q1","verse":"","text":""},{"style":"v","verse":"22","text":"Car j’ai observé les voies de l’Éternel,"},{"style":"q1","verse":"","text":"Et je n’ai point été coupable envers mon Dieu."},{"style":"q1","verse":"","text":""},{"style":"v","verse":"23","text":"Toutes ses ordonnances ont été devant moi,"},{"style":"q1","verse":"","text":"Et je ne me suis point écarté de ses lois."},{"style":"q1","verse":"","text":""},{"style":"v","verse":"24","text":"J’ai été sans reproche envers lui,"},{"style":"q1","verse":"","text":"Et je me suis tenu en garde contre mon iniquité."},{"style":"q1","verse":"","text":""},{"style":"v","verse":"25","text":"Aussi l’Éternel m’a rendu selon ma droiture,"},{"style":"q1","verse":"","text":"Selon ma pureté devant ses yeux."},{"style":"q1","verse":"","text":""},{"style":"v","verse":"26","text":"Avec celui qui est bon tu te montres bon,"},{"style":"q1","verse":"","text":"Avec l’homme droit tu agis selon la droiture,"},{"style":"q1","verse":"","text":""},{"style":"v","verse":"27","text":"Avec celui qui est pur tu te montres pur,"},{"style":"q1","verse":"","text":"Et avec le pervers tu agis selon sa perversité."},{"style":"q1","verse":"","text":""},{"style":"v","verse":"28","text":"Tu sauves le peuple qui s’humilie,"},{"style":"q1","verse":"","text":"Et de ton regard, tu abaisses les orgueilleux."},{"style":"q1","verse":"","text":""},{"style":"v","verse":"29","text":"Oui, tu es ma lumière, ô Éternel!"},{"style":"q1","verse":"","text":"L’Éternel éclaire mes ténèbres."},{"style":"q1","verse":"","text":""},{"style":"v","verse":"30","text":"Avec toi je me précipite sur une troupe en armes,"},{"style":"q1","verse":"","text":"Avec mon Dieu je franchis une muraille."},{"style":"q1","verse":"","text":""},{"style":"v","verse":"31","text":"\\x c \\xo 22.31 \\xt De 32:4. Da 4:37. Ap 15:3.\\x*Les voies de Dieu sont parfaites,"},{"style":"q1","verse":"","text":"\\x d \\xo 22.31 \\xt Ps 12:7; 119:140. Pr 30:5.\\x*La parole de l’Éternel est éprouvée;"},{"style":"q1","verse":"","text":"Il est un bouclier pour tous ceux qui se confient en lui."},{"style":"q1","verse":"","text":""},{"style":"v","verse":"32","text":"Car \\x e \\xo 22.32 \\xt De 32:19. 1 S 2:2. Ps 86:8. És 45:5.\\x*qui est Dieu, si ce n’est l’Éternel?"},{"style":"q1","verse":"","text":"Et qui est un rocher, si ce n’est notre Dieu?"},{"style":"q1","verse":"","text":""},{"style":"v","verse":"33","text":"C’est Dieu qui est ma puissante forteresse,"},{"style":"q1","verse":"","text":"Et qui me conduit dans la voie droite."},{"style":"q1","verse":"","text":""},{"style":"v","verse":"34","text":"Il rend mes pieds semblables à ceux des biches,"},{"style":"q1","verse":"","text":"Et il me place sur mes lieux élevés."},{"style":"q1","verse":"","text":""},{"style":"v","verse":"35","text":"Il exerce mes mains au combat,"},{"style":"q1","verse":"","text":"Et mes bras tendent l’arc d’airain."},{"style":"q1","verse":"","text":""},{"style":"v","verse":"36","text":"Tu me donnes le bouclier de ton salut,"},{"style":"q1","verse":"","text":"Et je deviens grand par ta bonté."},{"style":"q1","verse":"","text":""},{"style":"v","verse":"37","text":"Tu élargis le chemin sous mes pas,"},{"style":"q1","verse":"","text":"Et mes pieds ne chancellent point."},{"style":"q1","verse":"","text":""},{"style":"v","verse":"38","text":"Je poursuis mes ennemis, et je les détruis;"},{"style":"q1","verse":"","text":"Je ne reviens pas avant de les avoir anéantis."},{"style":"q1","verse":"","text":""},{"style":"v","verse":"39","text":"Je les anéantis, je les brise, et ils ne se relèvent plus;"},{"style":"q1","verse":"","text":"Ils tombent sous mes pieds."},{"style":"q1","verse":"","text":""},{"style":"v","verse":"40","text":"Tu me ceins de force pour le combat,"},{"style":"q1","verse":"","text":"Tu fais plier sous moi mes adversaires."},{"style":"q1","verse":"","text":""},{"style":"v","verse":"41","text":"Tu fais tourner le dos à mes ennemis devant moi,"},{"style":"q1","verse":"","text":"Et j’extermine ceux qui me haïssent."},{"style":"q1","verse":"","text":""},{"style":"v","verse":"42","text":"Ils regardent autour d’eux, et personne pour les sauver!"},{"style":"q1","verse":"","text":"Ils crient à l’Éternel, et il ne leur répond pas!"},{"style":"q1","verse":"","text":""},{"style":"v","verse":"43","text":"Je les broie comme la poussière de la terre,"},{"style":"q1","verse":"","text":"Je les écrase, je les foule, comme la boue des rues."},{"style":"q1","verse":"","text":""},{"style":"v","verse":"44","text":"Tu me délivres des dissensions de mon peuple;"},{"style":"q1","verse":"","text":"Tu me conserves pour chef des nations;"},{"style":"q1","verse":"","text":"Un peuple que je ne connaissais pas m’est asservi."},{"style":"q1","verse":"","text":""},{"style":"v","verse":"45","text":"Les fils de l’étranger me flattent,"},{"style":"q1","verse":"","text":"Ils m’obéissent au premier ordre."},{"style":"q1","verse":"","text":""},{"style":"v","verse":"46","text":"Les fils de l’étranger sont en défaillance,"},{"style":"q1","verse":"","text":"Ils tremblent hors de leurs forteresses."},{"style":"q1","verse":"","text":""},{"style":"v","verse":"47","text":"Vive l’Éternel, et béni soit mon rocher!"},{"style":"q1","verse":"","text":"Que Dieu, le rocher de mon salut, soit exalté,"},{"style":"q1","verse":"","text":""},{"style":"v","verse":"48","text":"Le Dieu qui est mon vengeur,"},{"style":"q1","verse":"","text":"Qui m’assujettit les peuples,"},{"style":"q1","verse":"","text":""},{"style":"v","verse":"49","text":"Et qui me fait échapper à mes ennemis!"},{"style":"q1","verse":"","text":"Tu m’élèves au-dessus de mes adversaires,"},{"style":"q1","verse":"","text":"Tu me délivres de l’homme violent."},{"style":"q1","verse":"","text":""},{"style":"v","verse":"50","text":"C’est pourquoi je te louerai parmi les \\x f \\xo 22.50 \\xt Ro 15:9.\\x*nations, ô Éternel!"},{"style":"q1","verse":"","text":"Et je chanterai à la gloire de ton nom."},{"style":"q1","verse":"","text":""},{"style":"v","verse":"51","text":"Il accorde de grandes délivrances à son roi,"},{"style":"q1","verse":"","text":"Et il fait miséricorde à son oint,"},{"style":"q1","verse":"","text":"A David, et à sa postérité, pour toujours."}]