[{"style":"r","text":"2 S 8:1-14. (Ps 44; 108:7, etc.)"},{"style":"p","text":""},{"style":"v","text":"Au chef des chantres. Sur le lis lyrique. Hymne de David, pour enseigner."},{"style":"b","text":""},{"style":"q1","text":""},{"style":"v","text":"\\x a \\xo 60.2 \\xt 2 S 8:3, 13. 1 Ch 18:3, 12.\\x*Lorsqu’il fit la guerre aux Syriens de Mésopotamie et aux Syriens de Tsoba, et que Joab revint et battit dans la vallée du sel douze mille Édomites."},{"style":"q1","text":""},{"style":"v","text":"O Dieu! \\x b \\xo 60.3 \\xt Ps 44:10.\\x*tu nous as repoussés, dispersés,"},{"style":"q1","text":"Tu t’es irrité: relève-nous!"},{"style":"q1","text":""},{"style":"v","text":"Tu as ébranlé la terre, tu l’as déchirée:"},{"style":"q1","text":"Répare ses brèches, car elle chancelle!"},{"style":"q1","text":""},{"style":"v","text":"Tu as fait voir à ton peuple des choses dures,"},{"style":"q1","text":"Tu nous as abreuvés d’un vin d’étourdissement."},{"style":"q1","text":""},{"style":"v","text":"Tu as donné à ceux qui te craignent une bannière,"},{"style":"q1","text":"Pour qu’elle s’élève à cause de la vérité. \\qs — Pause.\\qs*"},{"style":"q1","text":""},{"style":"v","text":"\\x c \\xo 60.7 \\xt Ps 108:7, etc.\\x*Afin que tes bien-aimés soient délivrés,"},{"style":"q1","text":"Sauve par ta droite, et exauce-nous!"},{"style":"q1","text":""},{"style":"v","text":"Dieu a dit dans sa sainteté: Je triompherai,"},{"style":"q1","text":"Je partagerai Sichem, je mesurerai la vallée de Succoth;"},{"style":"q1","text":""},{"style":"v","text":"A moi Galaad, à moi Manassé;"},{"style":"q1","text":"Éphraïm est le rempart de ma tête,"},{"style":"q1","text":"Et Juda, mon sceptre;"},{"style":"q1","text":""},{"style":"v","text":"Moab est le bassin où je me lave;"},{"style":"q1","text":"Je jette mon soulier sur Édom;"},{"style":"q1","text":"Pays des Philistins, pousse à mon sujet des cris de joie!"},{"style":"q1","text":""},{"style":"v","text":"Qui me mènera dans la ville forte?"},{"style":"q1","text":"Qui me conduira à Édom?"},{"style":"q1","text":""},{"style":"v","text":"N’est-ce pas toi, ô Dieu, qui nous as repoussés,"},{"style":"q1","text":"Et qui ne sortais plus, ô Dieu, avec nos armées?"},{"style":"q1","text":""},{"style":"v","text":"Donne-nous du secours contre la détresse!"},{"style":"q1","text":"Le secours de l’homme n’est que vanité."},{"style":"q1","text":""},{"style":"v","text":"Avec Dieu, nous ferons des exploits;"},{"style":"q1","text":"Il écrasera nos ennemis."}]