[{"style":"r","verse":"","text":"Ps 48. (És 2:2, 3; 60. Jé 3:17.)"},{"style":"q1","verse":"","text":""},{"style":"v","verse":"1","text":"Des fils de Koré. Psaume. Cantique."},{"style":"q1","verse":"","text":"Elle est fondée sur les montagnes saintes."},{"style":"q1","verse":"","text":""},{"style":"v","verse":"2","text":"L’Éternel aime les portes de Sion"},{"style":"q1","verse":"","text":"Plus que toutes les demeures de Jacob."},{"style":"q1","verse":"","text":""},{"style":"v","verse":"3","text":"Des choses glorieuses ont été dites sur toi,"},{"style":"q1","verse":"","text":"Ville de Dieu! \\qs — Pause.\\qs*"},{"style":"q1","verse":"","text":""},{"style":"v","verse":"4","text":"Je proclame l’Égypte et Babylone parmi ceux qui me connaissent;"},{"style":"q1","verse":"","text":"Voici, le pays des Philistins, Tyr, avec l’Éthiopie:"},{"style":"q1","verse":"","text":"C’est dans Sion qu’ils sont nés."},{"style":"q1","verse":"","text":""},{"style":"v","verse":"5","text":"Et de Sion il est dit: Tous y sont nés,"},{"style":"q1","verse":"","text":"Et c’est le Très-Haut qui l’affermit."},{"style":"q1","verse":"","text":""},{"style":"v","verse":"6","text":"L’Éternel compte en inscrivant les peuples:"},{"style":"q1","verse":"","text":"C’est là qu’ils sont nés. \\qs — Pause.\\qs*"},{"style":"q1","verse":"","text":""},{"style":"v","verse":"7","text":"Et ceux qui chantent et ceux qui dansent s’écrient:"},{"style":"q1","verse":"","text":"Toutes mes sources sont en toi."}]