[{"style":"r","text":"La 3:1-20. (Ps 6; 39; 89:39, etc.; 102:1-13.)"},{"style":"p","text":""},{"style":"v","text":"Cantique. Psaume des fils de Koré. Au chef des chantres. Pour chanter sur la flûte. Cantique d’Héman, l’Ezrachite."},{"style":"b","text":""},{"style":"q1","text":""},{"style":"v","text":"Éternel, Dieu de mon salut!"},{"style":"q1","text":"Je crie jour et nuit devant toi."},{"style":"q1","text":""},{"style":"v","text":"Que ma prière parvienne en ta présence!"},{"style":"q1","text":"Prête l’oreille à mes supplications!"},{"style":"q1","text":""},{"style":"v","text":"Car mon âme est rassasiée de maux,"},{"style":"q1","text":"Et ma vie s’approche du séjour des morts."},{"style":"q1","text":""},{"style":"v","text":"Je suis mis au rang de ceux qui descendent dans la fosse,"},{"style":"q1","text":"Je suis comme un homme qui n’a plus de force."},{"style":"q1","text":""},{"style":"v","text":"Je suis étendu parmi les morts,"},{"style":"q1","text":"Semblable à ceux qui sont tués et couchés dans le sépulcre,"},{"style":"q1","text":"A ceux dont tu n’as plus le souvenir,"},{"style":"q1","text":"Et qui sont séparés de ta main."},{"style":"q1","text":""},{"style":"v","text":"Tu m’as jeté dans une fosse profonde,"},{"style":"q1","text":"Dans les ténèbres, dans les abîmes."},{"style":"q1","text":""},{"style":"v","text":"Ta fureur s’appesantit sur moi,"},{"style":"q1","text":"Et tu m’accables de tous tes flots. \\qs — Pause.\\qs*"},{"style":"q1","text":""},{"style":"v","text":"Tu as éloigné de moi mes amis,"},{"style":"q1","text":"Tu m’as rendu pour eux un objet d’horreur;"},{"style":"q1","text":"Je suis enfermé et je ne puis sortir."},{"style":"q1","text":""},{"style":"v","text":"Mes yeux se consument dans la souffrance;"},{"style":"q1","text":"Je t’invoque tous les jours, ô Éternel!"},{"style":"q1","text":"J’étends vers toi les mains."},{"style":"q1","text":""},{"style":"v","text":"Est-ce pour les morts que tu fais des miracles?"},{"style":"q1","text":"Les morts se lèvent-ils pour te louer? \\qs — Pause.\\qs*"},{"style":"q1","text":""},{"style":"v","text":"Parle-t-on de ta bonté dans le sépulcre,"},{"style":"q1","text":"De ta fidélité dans l’abîme?"},{"style":"q1","text":""},{"style":"v","text":"Tes prodiges sont-ils connus dans les ténèbres,"},{"style":"q1","text":"Et ta justice dans la terre de l’oubli?"},{"style":"q1","text":""},{"style":"v","text":"O Éternel! J’implore ton secours,"},{"style":"q1","text":"Et le matin ma prière s’élève à toi."},{"style":"q1","text":""},{"style":"v","text":"Pourquoi, Éternel, repousses-tu mon âme?"},{"style":"q1","text":"Pourquoi me caches-tu ta face?"},{"style":"q1","text":""},{"style":"v","text":"Je suis malheureux et moribond dès ma jeunesse,"},{"style":"q1","text":"Je suis chargé de tes terreurs, je suis troublé."},{"style":"q1","text":""},{"style":"v","text":"Tes fureurs passent sur moi,"},{"style":"q1","text":"Tes terreurs m’anéantissent;"},{"style":"q1","text":""},{"style":"v","text":"Elles m’environnent tout le jour comme des eaux,"},{"style":"q1","text":"Elles m’enveloppent toutes à la fois."},{"style":"q1","text":""},{"style":"v","text":"Tu as éloigné de moi amis et compagnons;"},{"style":"q1","text":"Mes intimes ont disparu."}]